[
  {
    "birdId": "urocissa_erythroryncha",
    "chineseName": "红嘴蓝鹊",
    "englishName": "Red-billed Blue-Magpie",
    "scientificName": "Urocissa erythroryncha",
    "aliases": [],
    "order": {
      "zh": "雀形目",
      "en": "Passeriformes"
    },
    "family": {
      "zh": "Crows, Jays, and Magpies",
      "en": "Crows, Jays, and Magpies"
    },
    "dataLevel": "B",
    "sourceRefs": [
      "IOC World Bird List",
      "eBird",
      "eBird API v2 taxonomy"
    ],
    "updatedAt": "2026-05-07"
  },
  {
    "birdId": "pycnonotus_sinensis",
    "chineseName": "白头鹎",
    "englishName": "Light-vented Bulbul",
    "scientificName": "Pycnonotus sinensis",
    "aliases": [
      "白头翁"
    ],
    "order": {
      "zh": "雀形目",
      "en": "Passeriformes"
    },
    "family": {
      "zh": "Bulbuls",
      "en": "Bulbuls"
    },
    "dataLevel": "B",
    "sourceRefs": [
      "IOC World Bird List",
      "eBird",
      "eBird API v2 taxonomy"
    ],
    "updatedAt": "2026-05-07"
  },
  {
    "birdId": "alcedo_atthis",
    "chineseName": "普通翠鸟",
    "englishName": "Common Kingfisher",
    "scientificName": "Alcedo atthis",
    "aliases": [
      "翠鸟"
    ],
    "order": {
      "zh": "佛法僧目",
      "en": "Coraciiformes"
    },
    "family": {
      "zh": "Kingfishers",
      "en": "Kingfishers"
    },
    "dataLevel": "B",
    "sourceRefs": [
      "IOC World Bird List",
      "eBird",
      "eBird API v2 taxonomy"
    ],
    "updatedAt": "2026-05-07"
  },
  {
    "birdId": "himantopus_himantopus",
    "chineseName": "黑翅长脚鹬",
    "englishName": "Black-winged Stilt",
    "scientificName": "Himantopus himantopus",
    "aliases": [
      "高蹺鸻"
    ],
    "order": {
      "zh": "鸻形目",
      "en": "Charadriiformes"
    },
    "family": {
      "zh": "Stilts and Avocets",
      "en": "Stilts and Avocets"
    },
    "dataLevel": "C",
    "sourceRefs": [
      "IOC World Bird List",
      "eBird",
      "eBird API v2 taxonomy"
    ],
    "updatedAt": "2026-05-07"
  },
  {
    "birdId": "recurvirostra_avosetta",
    "chineseName": "反嘴鹬",
    "englishName": "Pied Avocet",
    "scientificName": "Recurvirostra avosetta",
    "aliases": [
      "反嘴鸻"
    ],
    "order": {
      "zh": "鸻形目",
      "en": "Charadriiformes"
    },
    "family": {
      "zh": "Stilts and Avocets",
      "en": "Stilts and Avocets"
    },
    "dataLevel": "C",
    "sourceRefs": [
      "IOC World Bird List",
      "eBird",
      "eBird API v2 taxonomy"
    ],
    "updatedAt": "2026-05-07"
  },
  {
    "birdId": "charadrius_dubius",
    "chineseName": "金眶鸻",
    "englishName": "Little Ringed Plover",
    "scientificName": "Thinornis dubius",
    "aliases": [],
    "order": {
      "zh": "鸻形目",
      "en": "Charadriiformes"
    },
    "family": {
      "zh": "Plovers and Lapwings",
      "en": "Plovers and Lapwings"
    },
    "dataLevel": "C",
    "sourceRefs": [
      "IOC World Bird List",
      "eBird",
      "eBird API v2 taxonomy"
    ],
    "updatedAt": "2026-05-07"
  },
  {
    "birdId": "charadrius_alexandrinus",
    "chineseName": "环颈鸻",
    "englishName": "Kentish Plover",
    "scientificName": "Anarhynchus alexandrinus",
    "aliases": [],
    "order": {
      "zh": "鸻形目",
      "en": "Charadriiformes"
    },
    "family": {
      "zh": "Plovers and Lapwings",
      "en": "Plovers and Lapwings"
    },
    "dataLevel": "C",
    "sourceRefs": [
      "IOC World Bird List",
      "eBird",
      "eBird API v2 taxonomy"
    ],
    "updatedAt": "2026-05-07"
  },
  {
    "birdId": "pluvialis_squatarola",
    "chineseName": "灰斑鸻",
    "englishName": "Black-bellied Plover",
    "scientificName": "Pluvialis squatarola",
    "aliases": [
      "灰斑鴴"
    ],
    "order": {
      "zh": "鸻形目",
      "en": "Charadriiformes"
    },
    "family": {
      "zh": "Plovers and Lapwings",
      "en": "Plovers and Lapwings"
    },
    "dataLevel": "C",
    "sourceRefs": [
      "IOC World Bird List",
      "eBird",
      "eBird API v2 taxonomy"
    ],
    "updatedAt": "2026-05-07"
  },
  {
    "birdId": "vanellus_vanellus",
    "chineseName": "凤头麦鸡",
    "englishName": "Northern Lapwing",
    "scientificName": "Vanellus vanellus",
    "aliases": [],
    "order": {
      "zh": "鸻形目",
      "en": "Charadriiformes"
    },
    "family": {
      "zh": "Plovers and Lapwings",
      "en": "Plovers and Lapwings"
    },
    "dataLevel": "C",
    "sourceRefs": [
      "IOC World Bird List",
      "eBird",
      "eBird API v2 taxonomy"
    ],
    "updatedAt": "2026-05-07"
  },
  {
    "birdId": "actitis_hypoleucos",
    "chineseName": "矶鹬",
    "englishName": "Common Sandpiper",
    "scientificName": "Actitis hypoleucos",
    "aliases": [],
    "order": {
      "zh": "鸻形目",
      "en": "Charadriiformes"
    },
    "family": {
      "zh": "Sandpipers and Allies",
      "en": "Sandpipers and Allies"
    },
    "dataLevel": "C",
    "sourceRefs": [
      "IOC World Bird List",
      "eBird",
      "eBird API v2 taxonomy"
    ],
    "updatedAt": "2026-05-07"
  },
  {
    "birdId": "tringa_totanus",
    "chineseName": "红脚鹬",
    "englishName": "Common Redshank",
    "scientificName": "Tringa totanus",
    "aliases": [],
    "order": {
      "zh": "鸻形目",
      "en": "Charadriiformes"
    },
    "family": {
      "zh": "Sandpipers and Allies",
      "en": "Sandpipers and Allies"
    },
    "dataLevel": "C",
    "sourceRefs": [
      "IOC World Bird List",
      "eBird",
      "eBird API v2 taxonomy"
    ],
    "updatedAt": "2026-05-07"
  },
  {
    "birdId": "tringa_nebularia",
    "chineseName": "青脚鹬",
    "englishName": "Common Greenshank",
    "scientificName": "Tringa nebularia",
    "aliases": [],
    "order": {
      "zh": "鸻形目",
      "en": "Charadriiformes"
    },
    "family": {
      "zh": "Sandpipers and Allies",
      "en": "Sandpipers and Allies"
    },
    "dataLevel": "C",
    "sourceRefs": [
      "IOC World Bird List",
      "eBird",
      "eBird API v2 taxonomy"
    ],
    "updatedAt": "2026-05-07"
  },
  {
    "birdId": "numenius_arquata",
    "chineseName": "白腰杓鹬",
    "englishName": "Eurasian Curlew",
    "scientificName": "Numenius arquata",
    "aliases": [],
    "order": {
      "zh": "鸻形目",
      "en": "Charadriiformes"
    },
    "family": {
      "zh": "Sandpipers and Allies",
      "en": "Sandpipers and Allies"
    },
    "dataLevel": "C",
    "sourceRefs": [
      "IOC World Bird List",
      "eBird",
      "eBird API v2 taxonomy"
    ],
    "updatedAt": "2026-05-07"
  },
  {
    "birdId": "pluvialis_fulva",
    "chineseName": "金斑鸻",
    "englishName": "Pacific Golden-Plover",
    "scientificName": "Pluvialis fulva",
    "aliases": [],
    "order": {
      "zh": "鸻形目",
      "en": "Charadriiformes"
    },
    "family": {
      "zh": "Plovers and Lapwings",
      "en": "Plovers and Lapwings"
    },
    "dataLevel": "C",
    "sourceRefs": [
      "IOC World Bird List",
      "Avibase Hebei checklist",
      "eBird API v2 taxonomy"
    ],
    "updatedAt": "2026-05-07"
  },
  {
    "birdId": "charadrius_mongolus",
    "chineseName": "蒙古沙鸻",
    "englishName": "Lesser Sand Plover",
    "scientificName": "Charadrius mongolus",
    "aliases": [],
    "order": {
      "zh": "鸻形目",
      "en": "Charadriiformes"
    },
    "family": {
      "zh": "鸻科",
      "en": "Charadriidae"
    },
    "dataLevel": "C",
    "sourceRefs": [
      "IOC World Bird List",
      "Avibase Hebei checklist"
    ],
    "updatedAt": "2026-05-07"
  },
  {
    "birdId": "limosa_lapponica",
    "chineseName": "斑尾塍鹬",
    "englishName": "Bar-tailed Godwit",
    "scientificName": "Limosa lapponica",
    "aliases": [],
    "order": {
      "zh": "鸻形目",
      "en": "Charadriiformes"
    },
    "family": {
      "zh": "Sandpipers and Allies",
      "en": "Sandpipers and Allies"
    },
    "dataLevel": "C",
    "sourceRefs": [
      "IOC World Bird List",
      "Avibase Hebei checklist",
      "eBird API v2 taxonomy"
    ],
    "updatedAt": "2026-05-07"
  },
  {
    "birdId": "limosa_limosa",
    "chineseName": "黑尾塍鹬",
    "englishName": "Black-tailed Godwit",
    "scientificName": "Limosa limosa",
    "aliases": [],
    "order": {
      "zh": "鸻形目",
      "en": "Charadriiformes"
    },
    "family": {
      "zh": "Sandpipers and Allies",
      "en": "Sandpipers and Allies"
    },
    "dataLevel": "C",
    "sourceRefs": [
      "IOC World Bird List",
      "Avibase Hebei checklist",
      "eBird API v2 taxonomy"
    ],
    "updatedAt": "2026-05-07"
  },
  {
    "birdId": "numenius_madagascariensis",
    "chineseName": "大杓鹬",
    "englishName": "Far Eastern Curlew",
    "scientificName": "Numenius madagascariensis",
    "aliases": [],
    "order": {
      "zh": "鸻形目",
      "en": "Charadriiformes"
    },
    "family": {
      "zh": "Sandpipers and Allies",
      "en": "Sandpipers and Allies"
    },
    "dataLevel": "C",
    "sourceRefs": [
      "IOC World Bird List",
      "Avibase Hebei checklist",
      "eBird API v2 taxonomy"
    ],
    "updatedAt": "2026-05-07"
  },
  {
    "birdId": "calidris_tenuirostris",
    "chineseName": "大滨鹬",
    "englishName": "Great Knot",
    "scientificName": "Calidris tenuirostris",
    "aliases": [],
    "order": {
      "zh": "鸻形目",
      "en": "Charadriiformes"
    },
    "family": {
      "zh": "Sandpipers and Allies",
      "en": "Sandpipers and Allies"
    },
    "dataLevel": "C",
    "sourceRefs": [
      "IOC World Bird List",
      "Avibase Hebei checklist",
      "eBird API v2 taxonomy"
    ],
    "updatedAt": "2026-05-07"
  },
  {
    "birdId": "calidris_canutus",
    "chineseName": "红腹滨鹬",
    "englishName": "Red Knot",
    "scientificName": "Calidris canutus",
    "aliases": [],
    "order": {
      "zh": "鸻形目",
      "en": "Charadriiformes"
    },
    "family": {
      "zh": "Sandpipers and Allies",
      "en": "Sandpipers and Allies"
    },
    "dataLevel": "C",
    "sourceRefs": [
      "IOC World Bird List",
      "Avibase Hebei checklist",
      "eBird API v2 taxonomy"
    ],
    "updatedAt": "2026-05-07"
  },
  {
    "birdId": "calidris_acuminata",
    "chineseName": "尖尾滨鹬",
    "englishName": "Sharp-tailed Sandpiper",
    "scientificName": "Calidris acuminata",
    "aliases": [],
    "order": {
      "zh": "鸻形目",
      "en": "Charadriiformes"
    },
    "family": {
      "zh": "Sandpipers and Allies",
      "en": "Sandpipers and Allies"
    },
    "dataLevel": "C",
    "sourceRefs": [
      "IOC World Bird List",
      "Avibase Hebei checklist",
      "eBird API v2 taxonomy"
    ],
    "updatedAt": "2026-05-07"
  },
  {
    "birdId": "calidris_ruficollis",
    "chineseName": "红颈滨鹬",
    "englishName": "Red-necked Stint",
    "scientificName": "Calidris ruficollis",
    "aliases": [],
    "order": {
      "zh": "鸻形目",
      "en": "Charadriiformes"
    },
    "family": {
      "zh": "Sandpipers and Allies",
      "en": "Sandpipers and Allies"
    },
    "dataLevel": "C",
    "sourceRefs": [
      "IOC World Bird List",
      "Avibase Hebei checklist",
      "eBird API v2 taxonomy"
    ],
    "updatedAt": "2026-05-07"
  },
  {
    "birdId": "tringa_stagnatilis",
    "chineseName": "泽鹬",
    "englishName": "Marsh Sandpiper",
    "scientificName": "Tringa stagnatilis",
    "aliases": [],
    "order": {
      "zh": "鸻形目",
      "en": "Charadriiformes"
    },
    "family": {
      "zh": "Sandpipers and Allies",
      "en": "Sandpipers and Allies"
    },
    "dataLevel": "C",
    "sourceRefs": [
      "IOC World Bird List",
      "Avibase Hebei checklist",
      "eBird API v2 taxonomy"
    ],
    "updatedAt": "2026-05-07"
  },
  {
    "birdId": "tringa_glareola",
    "chineseName": "林鹬",
    "englishName": "Wood Sandpiper",
    "scientificName": "Tringa glareola",
    "aliases": [],
    "order": {
      "zh": "鸻形目",
      "en": "Charadriiformes"
    },
    "family": {
      "zh": "Sandpipers and Allies",
      "en": "Sandpipers and Allies"
    },
    "dataLevel": "C",
    "sourceRefs": [
      "IOC World Bird List",
      "Avibase Hebei checklist",
      "eBird API v2 taxonomy"
    ],
    "updatedAt": "2026-05-07"
  },
  {
    "birdId": "tringa_erythropus",
    "chineseName": "鹤鹬",
    "englishName": "Spotted Redshank",
    "scientificName": "Tringa erythropus",
    "aliases": [],
    "order": {
      "zh": "鸻形目",
      "en": "Charadriiformes"
    },
    "family": {
      "zh": "Sandpipers and Allies",
      "en": "Sandpipers and Allies"
    },
    "dataLevel": "C",
    "sourceRefs": [
      "IOC World Bird List",
      "Avibase Hebei checklist",
      "eBird API v2 taxonomy"
    ],
    "updatedAt": "2026-05-07"
  },
  {
    "birdId": "xenus_cinereus",
    "chineseName": "翘嘴鹬",
    "englishName": "Terek Sandpiper",
    "scientificName": "Xenus cinereus",
    "aliases": [],
    "order": {
      "zh": "鸻形目",
      "en": "Charadriiformes"
    },
    "family": {
      "zh": "Sandpipers and Allies",
      "en": "Sandpipers and Allies"
    },
    "dataLevel": "C",
    "sourceRefs": [
      "IOC World Bird List",
      "Avibase Hebei checklist",
      "eBird API v2 taxonomy"
    ],
    "updatedAt": "2026-05-07"
  },
  {
    "birdId": "tringa_brevipes",
    "chineseName": "灰尾漂鹬",
    "englishName": "Gray-tailed Tattler",
    "scientificName": "Tringa brevipes",
    "aliases": [],
    "order": {
      "zh": "鸻形目",
      "en": "Charadriiformes"
    },
    "family": {
      "zh": "Sandpipers and Allies",
      "en": "Sandpipers and Allies"
    },
    "dataLevel": "C",
    "sourceRefs": [
      "IOC World Bird List",
      "Avibase Hebei checklist",
      "eBird API v2 taxonomy"
    ],
    "updatedAt": "2026-05-07"
  },
  {
    "birdId": "spbsan1",
    "chineseName": "琵嘴鹬",
    "englishName": "琵嘴鷸",
    "scientificName": "Calidris pygmaea",
    "aliases": [],
    "order": {
      "zh": "鸻形目",
      "en": "Charadriiformes"
    },
    "family": {
      "zh": "Sandpipers and Allies",
      "en": "Sandpipers and Allies"
    },
    "dataLevel": "C",
    "sourceRefs": [
      "eBird API v2 taxonomy",
      "eBird CN-13 Hebei checklist"
    ],
    "updatedAt": "2026-05-07"
  },
  {
    "birdId": "fragul",
    "chineseName": "弗氏鸥",
    "englishName": "弗氏鷗",
    "scientificName": "Leucophaeus pipixcan",
    "aliases": [],
    "order": {
      "zh": "鸻形目",
      "en": "Charadriiformes"
    },
    "family": {
      "zh": "Gulls, Terns, and Skimmers",
      "en": "Gulls, Terns, and Skimmers"
    },
    "dataLevel": "C",
    "sourceRefs": [
      "eBird API v2 taxonomy",
      "eBird CN-13 Hebei checklist"
    ],
    "updatedAt": "2026-05-07"
  },
  {
    "birdId": "litcur",
    "chineseName": "小杓鹬",
    "englishName": "小杓鷸",
    "scientificName": "Numenius minutus",
    "aliases": [],
    "order": {
      "zh": "鸻形目",
      "en": "Charadriiformes"
    },
    "family": {
      "zh": "Sandpipers and Allies",
      "en": "Sandpipers and Allies"
    },
    "dataLevel": "C",
    "sourceRefs": [
      "eBird API v2 taxonomy",
      "eBird CN-13 Hebei checklist"
    ],
    "updatedAt": "2026-05-07"
  },
  {
    "birdId": "dunlin",
    "chineseName": "黑腹滨鹬",
    "englishName": "黑腹濱鷸",
    "scientificName": "Calidris alpina",
    "aliases": [],
    "order": {
      "zh": "鸻形目",
      "en": "Charadriiformes"
    },
    "family": {
      "zh": "Sandpipers and Allies",
      "en": "Sandpipers and Allies"
    },
    "dataLevel": "C",
    "sourceRefs": [
      "eBird API v2 taxonomy",
      "eBird CN-13 Hebei checklist"
    ],
    "updatedAt": "2026-05-07"
  },
  {
    "birdId": "bnhgul1",
    "chineseName": "棕头鸥",
    "englishName": "棕頭鷗",
    "scientificName": "Chroicocephalus brunnicephalus",
    "aliases": [],
    "order": {
      "zh": "鸻形目",
      "en": "Charadriiformes"
    },
    "family": {
      "zh": "Gulls, Terns, and Skimmers",
      "en": "Gulls, Terns, and Skimmers"
    },
    "dataLevel": "C",
    "sourceRefs": [
      "eBird API v2 taxonomy",
      "eBird CN-13 Hebei checklist"
    ],
    "updatedAt": "2026-05-07"
  },
  {
    "birdId": "grpsni1",
    "chineseName": "彩鹬",
    "englishName": "彩鷸",
    "scientificName": "Rostratula benghalensis",
    "aliases": [],
    "order": {
      "zh": "鸻形目",
      "en": "Charadriiformes"
    },
    "family": {
      "zh": "Painted-Snipes",
      "en": "Painted-Snipes"
    },
    "dataLevel": "C",
    "sourceRefs": [
      "eBird API v2 taxonomy",
      "eBird CN-13 Hebei checklist"
    ],
    "updatedAt": "2026-05-07"
  },
  {
    "birdId": "solsni1",
    "chineseName": "孤田鹬",
    "englishName": "孤田鷸",
    "scientificName": "Gallinago solitaria",
    "aliases": [],
    "order": {
      "zh": "鸻形目",
      "en": "Charadriiformes"
    },
    "family": {
      "zh": "Sandpipers and Allies",
      "en": "Sandpipers and Allies"
    },
    "dataLevel": "C",
    "sourceRefs": [
      "eBird API v2 taxonomy",
      "eBird CN-13 Hebei checklist"
    ],
    "updatedAt": "2026-05-07"
  },
  {
    "birdId": "rudtur",
    "chineseName": "翻石鹬",
    "englishName": "翻石鷸",
    "scientificName": "Arenaria interpres",
    "aliases": [],
    "order": {
      "zh": "鸻形目",
      "en": "Charadriiformes"
    },
    "family": {
      "zh": "Sandpipers and Allies",
      "en": "Sandpipers and Allies"
    },
    "dataLevel": "C",
    "sourceRefs": [
      "eBird API v2 taxonomy",
      "eBird CN-13 Hebei checklist"
    ],
    "updatedAt": "2026-05-07"
  },
  {
    "birdId": "bktgul",
    "chineseName": "黑尾鸥",
    "englishName": "黑尾鷗",
    "scientificName": "Larus crassirostris",
    "aliases": [],
    "order": {
      "zh": "鸻形目",
      "en": "Charadriiformes"
    },
    "family": {
      "zh": "Gulls, Terns, and Skimmers",
      "en": "Gulls, Terns, and Skimmers"
    },
    "dataLevel": "C",
    "sourceRefs": [
      "eBird API v2 taxonomy",
      "eBird CN-13 Hebei checklist"
    ],
    "updatedAt": "2026-05-07"
  },
  {
    "birdId": "asidow1",
    "chineseName": "半蹼鹬",
    "englishName": "半蹼鷸",
    "scientificName": "Limnodromus semipalmatus",
    "aliases": [],
    "order": {
      "zh": "鸻形目",
      "en": "Charadriiformes"
    },
    "family": {
      "zh": "Sandpipers and Allies",
      "en": "Sandpipers and Allies"
    },
    "dataLevel": "C",
    "sourceRefs": [
      "eBird API v2 taxonomy",
      "eBird CN-13 Hebei checklist"
    ],
    "updatedAt": "2026-05-07"
  },
  {
    "birdId": "pitsni",
    "chineseName": "针尾鹬",
    "englishName": "針尾鷸",
    "scientificName": "Gallinago stenura",
    "aliases": [],
    "order": {
      "zh": "鸻形目",
      "en": "Charadriiformes"
    },
    "family": {
      "zh": "Sandpipers and Allies",
      "en": "Sandpipers and Allies"
    },
    "dataLevel": "C",
    "sourceRefs": [
      "eBird API v2 taxonomy",
      "eBird CN-13 Hebei checklist"
    ],
    "updatedAt": "2026-05-07"
  },
  {
    "birdId": "lessap2",
    "chineseName": "蒙古鸻",
    "englishName": "蒙古鴴",
    "scientificName": "Anarhynchus mongolus",
    "aliases": [],
    "order": {
      "zh": "鸻形目",
      "en": "Charadriiformes"
    },
    "family": {
      "zh": "Plovers and Lapwings",
      "en": "Plovers and Lapwings"
    },
    "dataLevel": "C",
    "sourceRefs": [
      "eBird API v2 taxonomy",
      "eBird CN-13 Hebei checklist"
    ],
    "updatedAt": "2026-05-07"
  },
  {
    "birdId": "whwter",
    "chineseName": "白翅黑燕鸥",
    "englishName": "白翅黑燕鷗",
    "scientificName": "Chlidonias leucopterus",
    "aliases": [],
    "order": {
      "zh": "鸻形目",
      "en": "Charadriiformes"
    },
    "family": {
      "zh": "Gulls, Terns, and Skimmers",
      "en": "Gulls, Terns, and Skimmers"
    },
    "dataLevel": "C",
    "sourceRefs": [
      "eBird API v2 taxonomy",
      "eBird CN-13 Hebei checklist"
    ],
    "updatedAt": "2026-05-07"
  },
  {
    "birdId": "lobmur",
    "chineseName": "Long-billed Murrelet",
    "englishName": "Long-billed Murrelet",
    "scientificName": "Brachyramphus perdix",
    "aliases": [],
    "order": {
      "zh": "鸻形目",
      "en": "Charadriiformes"
    },
    "family": {
      "zh": "Auks, Murres, and Puffins",
      "en": "Auks, Murres, and Puffins"
    },
    "dataLevel": "C",
    "sourceRefs": [
      "eBird API v2 taxonomy",
      "eBird CN-13 Hebei checklist"
    ],
    "updatedAt": "2026-05-07"
  },
  {
    "birdId": "glagul",
    "chineseName": "北極鸥",
    "englishName": "北極鷗",
    "scientificName": "Larus hyperboreus",
    "aliases": [],
    "order": {
      "zh": "鸻形目",
      "en": "Charadriiformes"
    },
    "family": {
      "zh": "Gulls, Terns, and Skimmers",
      "en": "Gulls, Terns, and Skimmers"
    },
    "dataLevel": "C",
    "sourceRefs": [
      "eBird API v2 taxonomy",
      "eBird CN-13 Hebei checklist"
    ],
    "updatedAt": "2026-05-07"
  },
  {
    "birdId": "ibisbi1",
    "chineseName": "Ibisbill",
    "englishName": "Ibisbill",
    "scientificName": "Ibidorhyncha struthersii",
    "aliases": [],
    "order": {
      "zh": "鸻形目",
      "en": "Charadriiformes"
    },
    "family": {
      "zh": "Ibisbill",
      "en": "Ibisbill"
    },
    "dataLevel": "C",
    "sourceRefs": [
      "eBird API v2 taxonomy",
      "eBird CN-13 Hebei checklist"
    ],
    "updatedAt": "2026-05-07"
  },
  {
    "birdId": "pecsan",
    "chineseName": "美洲尖尾滨鹬",
    "englishName": "美洲尖尾濱鷸",
    "scientificName": "Calidris melanotos",
    "aliases": [],
    "order": {
      "zh": "鸻形目",
      "en": "Charadriiformes"
    },
    "family": {
      "zh": "Sandpipers and Allies",
      "en": "Sandpipers and Allies"
    },
    "dataLevel": "C",
    "sourceRefs": [
      "eBird API v2 taxonomy",
      "eBird CN-13 Hebei checklist"
    ],
    "updatedAt": "2026-05-07"
  },
  {
    "birdId": "gyhlap1",
    "chineseName": "跳鸻",
    "englishName": "跳鴴",
    "scientificName": "Vanellus cinereus",
    "aliases": [],
    "order": {
      "zh": "鸻形目",
      "en": "Charadriiformes"
    },
    "family": {
      "zh": "Plovers and Lapwings",
      "en": "Plovers and Lapwings"
    },
    "dataLevel": "C",
    "sourceRefs": [
      "eBird API v2 taxonomy",
      "eBird CN-13 Hebei checklist"
    ],
    "updatedAt": "2026-05-07"
  },
  {
    "birdId": "lecter2",
    "chineseName": "小凤头燕鸥",
    "englishName": "小鳳頭燕鷗",
    "scientificName": "Thalasseus bengalensis",
    "aliases": [],
    "order": {
      "zh": "鸻形目",
      "en": "Charadriiformes"
    },
    "family": {
      "zh": "Gulls, Terns, and Skimmers",
      "en": "Gulls, Terns, and Skimmers"
    },
    "dataLevel": "C",
    "sourceRefs": [
      "eBird API v2 taxonomy",
      "eBird CN-13 Hebei checklist"
    ],
    "updatedAt": "2026-05-07"
  },
  {
    "birdId": "bklkit",
    "chineseName": "三趾鸥",
    "englishName": "三趾鷗",
    "scientificName": "Rissa tridactyla",
    "aliases": [],
    "order": {
      "zh": "鸻形目",
      "en": "Charadriiformes"
    },
    "family": {
      "zh": "Gulls, Terns, and Skimmers",
      "en": "Gulls, Terns, and Skimmers"
    },
    "dataLevel": "C",
    "sourceRefs": [
      "eBird API v2 taxonomy",
      "eBird CN-13 Hebei checklist"
    ],
    "updatedAt": "2026-05-07"
  },
  {
    "birdId": "litgul",
    "chineseName": "小鸥",
    "englishName": "小鷗",
    "scientificName": "Hydrocoloeus minutus",
    "aliases": [],
    "order": {
      "zh": "鸻形目",
      "en": "Charadriiformes"
    },
    "family": {
      "zh": "Gulls, Terns, and Skimmers",
      "en": "Gulls, Terns, and Skimmers"
    },
    "dataLevel": "C",
    "sourceRefs": [
      "eBird API v2 taxonomy",
      "eBird CN-13 Hebei checklist"
    ],
    "updatedAt": "2026-05-07"
  },
  {
    "birdId": "lobdow",
    "chineseName": "长嘴半蹼鹬",
    "englishName": "長嘴半蹼鷸",
    "scientificName": "Limnodromus scolopaceus",
    "aliases": [],
    "order": {
      "zh": "鸻形目",
      "en": "Charadriiformes"
    },
    "family": {
      "zh": "Sandpipers and Allies",
      "en": "Sandpipers and Allies"
    },
    "dataLevel": "C",
    "sourceRefs": [
      "eBird API v2 taxonomy",
      "eBird CN-13 Hebei checklist"
    ],
    "updatedAt": "2026-05-07"
  },
  {
    "birdId": "oripra",
    "chineseName": "燕鸻",
    "englishName": "燕鴴",
    "scientificName": "Glareola maldivarum",
    "aliases": [],
    "order": {
      "zh": "鸻形目",
      "en": "Charadriiformes"
    },
    "family": {
      "zh": "Pratincoles and Coursers",
      "en": "Pratincoles and Coursers"
    },
    "dataLevel": "C",
    "sourceRefs": [
      "eBird API v2 taxonomy",
      "eBird CN-13 Hebei checklist"
    ],
    "updatedAt": "2026-05-07"
  },
  {
    "birdId": "whimbr5",
    "chineseName": "中杓鹬",
    "englishName": "中杓鷸",
    "scientificName": "Numenius phaeopus",
    "aliases": [],
    "order": {
      "zh": "鸻形目",
      "en": "Charadriiformes"
    },
    "family": {
      "zh": "Sandpipers and Allies",
      "en": "Sandpipers and Allies"
    },
    "dataLevel": "C",
    "sourceRefs": [
      "eBird API v2 taxonomy",
      "eBird CN-13 Hebei checklist"
    ],
    "updatedAt": "2026-05-07"
  },
  {
    "birdId": "corplo",
    "chineseName": "环颈鸻",
    "englishName": "環頸鴴",
    "scientificName": "Charadrius hiaticula",
    "aliases": [],
    "order": {
      "zh": "鸻形目",
      "en": "Charadriiformes"
    },
    "family": {
      "zh": "Plovers and Lapwings",
      "en": "Plovers and Lapwings"
    },
    "dataLevel": "C",
    "sourceRefs": [
      "eBird API v2 taxonomy",
      "eBird CN-13 Hebei checklist"
    ],
    "updatedAt": "2026-05-07"
  },
  {
    "birdId": "ancmur",
    "chineseName": "扁嘴海雀",
    "englishName": "扁嘴海雀",
    "scientificName": "Synthliboramphus antiquus",
    "aliases": [],
    "order": {
      "zh": "鸻形目",
      "en": "Charadriiformes"
    },
    "family": {
      "zh": "Auks, Murres, and Puffins",
      "en": "Auks, Murres, and Puffins"
    },
    "dataLevel": "C",
    "sourceRefs": [
      "eBird API v2 taxonomy",
      "eBird CN-13 Hebei checklist"
    ],
    "updatedAt": "2026-05-07"
  },
  {
    "birdId": "slbgul",
    "chineseName": "灰背鸥",
    "englishName": "灰背鷗",
    "scientificName": "Larus schistisagus",
    "aliases": [],
    "order": {
      "zh": "鸻形目",
      "en": "Charadriiformes"
    },
    "family": {
      "zh": "Gulls, Terns, and Skimmers",
      "en": "Gulls, Terns, and Skimmers"
    },
    "dataLevel": "C",
    "sourceRefs": [
      "eBird API v2 taxonomy",
      "eBird CN-13 Hebei checklist"
    ],
    "updatedAt": "2026-05-07"
  },
  {
    "birdId": "yelbut1",
    "chineseName": "黄脚三趾鹌",
    "englishName": "黃腳三趾鶉",
    "scientificName": "Turnix tanki",
    "aliases": [],
    "order": {
      "zh": "鸻形目",
      "en": "Charadriiformes"
    },
    "family": {
      "zh": "Buttonquail",
      "en": "Buttonquail"
    },
    "dataLevel": "C",
    "sourceRefs": [
      "eBird API v2 taxonomy",
      "eBird CN-13 Hebei checklist"
    ],
    "updatedAt": "2026-05-07"
  },
  {
    "birdId": "norgre1",
    "chineseName": "諾氏鹬",
    "englishName": "諾氏鷸",
    "scientificName": "Tringa guttifer",
    "aliases": [],
    "order": {
      "zh": "鸻形目",
      "en": "Charadriiformes"
    },
    "family": {
      "zh": "Sandpipers and Allies",
      "en": "Sandpipers and Allies"
    },
    "dataLevel": "C",
    "sourceRefs": [
      "eBird API v2 taxonomy",
      "eBird CN-13 Hebei checklist"
    ],
    "updatedAt": "2026-05-07"
  },
  {
    "birdId": "phtjac1",
    "chineseName": "水雉",
    "englishName": "水雉",
    "scientificName": "Hydrophasianus chirurgus",
    "aliases": [],
    "order": {
      "zh": "鸻形目",
      "en": "Charadriiformes"
    },
    "family": {
      "zh": "Jacanas",
      "en": "Jacanas"
    },
    "dataLevel": "C",
    "sourceRefs": [
      "eBird API v2 taxonomy",
      "eBird CN-13 Hebei checklist"
    ],
    "updatedAt": "2026-05-07"
  },
  {
    "birdId": "caster1",
    "chineseName": "裏海燕鸥",
    "englishName": "裏海燕鷗",
    "scientificName": "Hydroprogne caspia",
    "aliases": [],
    "order": {
      "zh": "鸻形目",
      "en": "Charadriiformes"
    },
    "family": {
      "zh": "Gulls, Terns, and Skimmers",
      "en": "Gulls, Terns, and Skimmers"
    },
    "dataLevel": "C",
    "sourceRefs": [
      "eBird API v2 taxonomy",
      "eBird CN-13 Hebei checklist"
    ],
    "updatedAt": "2026-05-07"
  },
  {
    "birdId": "cursan",
    "chineseName": "弯嘴滨鹬",
    "englishName": "彎嘴濱鷸",
    "scientificName": "Calidris ferruginea",
    "aliases": [],
    "order": {
      "zh": "鸻形目",
      "en": "Charadriiformes"
    },
    "family": {
      "zh": "Sandpipers and Allies",
      "en": "Sandpipers and Allies"
    },
    "dataLevel": "C",
    "sourceRefs": [
      "eBird API v2 taxonomy",
      "eBird CN-13 Hebei checklist"
    ],
    "updatedAt": "2026-05-07"
  },
  {
    "birdId": "swisni1",
    "chineseName": "中地鹬",
    "englishName": "中地鷸",
    "scientificName": "Gallinago megala",
    "aliases": [],
    "order": {
      "zh": "鸻形目",
      "en": "Charadriiformes"
    },
    "family": {
      "zh": "Sandpipers and Allies",
      "en": "Sandpipers and Allies"
    },
    "dataLevel": "C",
    "sourceRefs": [
      "eBird API v2 taxonomy",
      "eBird CN-13 Hebei checklist"
    ],
    "updatedAt": "2026-05-07"
  },
  {
    "birdId": "brbsan",
    "chineseName": "寬嘴鹬",
    "englishName": "寬嘴鷸",
    "scientificName": "Calidris falcinellus",
    "aliases": [],
    "order": {
      "zh": "鸻形目",
      "en": "Charadriiformes"
    },
    "family": {
      "zh": "Sandpipers and Allies",
      "en": "Sandpipers and Allies"
    },
    "dataLevel": "C",
    "sourceRefs": [
      "eBird API v2 taxonomy",
      "eBird CN-13 Hebei checklist"
    ],
    "updatedAt": "2026-05-07"
  },
  {
    "birdId": "grsplo",
    "chineseName": "铁嘴鸻",
    "englishName": "鐵嘴鴴",
    "scientificName": "Anarhynchus leschenaultii",
    "aliases": [],
    "order": {
      "zh": "鸻形目",
      "en": "Charadriiformes"
    },
    "family": {
      "zh": "Plovers and Lapwings",
      "en": "Plovers and Lapwings"
    },
    "dataLevel": "C",
    "sourceRefs": [
      "eBird API v2 taxonomy",
      "eBird CN-13 Hebei checklist"
    ],
    "updatedAt": "2026-05-07"
  },
  {
    "birdId": "eurwoo",
    "chineseName": "山鹬",
    "englishName": "山鷸",
    "scientificName": "Scolopax rusticola",
    "aliases": [],
    "order": {
      "zh": "鸻形目",
      "en": "Charadriiformes"
    },
    "family": {
      "zh": "Sandpipers and Allies",
      "en": "Sandpipers and Allies"
    },
    "dataLevel": "C",
    "sourceRefs": [
      "eBird API v2 taxonomy",
      "eBird CN-13 Hebei checklist"
    ],
    "updatedAt": "2026-05-07"
  },
  {
    "birdId": "lotsti",
    "chineseName": "长趾滨鹬",
    "englishName": "長趾濱鷸",
    "scientificName": "Calidris subminuta",
    "aliases": [],
    "order": {
      "zh": "鸻形目",
      "en": "Charadriiformes"
    },
    "family": {
      "zh": "Sandpipers and Allies",
      "en": "Sandpipers and Allies"
    },
    "dataLevel": "C",
    "sourceRefs": [
      "eBird API v2 taxonomy",
      "eBird CN-13 Hebei checklist"
    ],
    "updatedAt": "2026-05-07"
  },
  {
    "birdId": "temsti",
    "chineseName": "丹氏滨鹬",
    "englishName": "丹氏濱鷸",
    "scientificName": "Calidris temminckii",
    "aliases": [],
    "order": {
      "zh": "鸻形目",
      "en": "Charadriiformes"
    },
    "family": {
      "zh": "Sandpipers and Allies",
      "en": "Sandpipers and Allies"
    },
    "dataLevel": "C",
    "sourceRefs": [
      "eBird API v2 taxonomy",
      "eBird CN-13 Hebei checklist"
    ],
    "updatedAt": "2026-05-07"
  },
  {
    "birdId": "lbbgul",
    "chineseName": "小黑背鸥",
    "englishName": "小黑背鷗",
    "scientificName": "Larus fuscus",
    "aliases": [],
    "order": {
      "zh": "鸻形目",
      "en": "Charadriiformes"
    },
    "family": {
      "zh": "Gulls, Terns, and Skimmers",
      "en": "Gulls, Terns, and Skimmers"
    },
    "dataLevel": "C",
    "sourceRefs": [
      "eBird API v2 taxonomy",
      "eBird CN-13 Hebei checklist"
    ],
    "updatedAt": "2026-05-07"
  },
  {
    "birdId": "sooter1",
    "chineseName": "烏领燕鸥",
    "englishName": "烏領燕鷗",
    "scientificName": "Onychoprion fuscatus",
    "aliases": [],
    "order": {
      "zh": "鸻形目",
      "en": "Charadriiformes"
    },
    "family": {
      "zh": "Gulls, Terns, and Skimmers",
      "en": "Gulls, Terns, and Skimmers"
    },
    "dataLevel": "C",
    "sourceRefs": [
      "eBird API v2 taxonomy",
      "eBird CN-13 Hebei checklist"
    ],
    "updatedAt": "2026-05-07"
  },
  {
    "birdId": "lotjae",
    "chineseName": "长尾賊鸥",
    "englishName": "長尾賊鷗",
    "scientificName": "Stercorarius longicaudus",
    "aliases": [],
    "order": {
      "zh": "鸻形目",
      "en": "Charadriiformes"
    },
    "family": {
      "zh": "Skuas and Jaegers",
      "en": "Skuas and Jaegers"
    },
    "dataLevel": "C",
    "sourceRefs": [
      "eBird API v2 taxonomy",
      "eBird CN-13 Hebei checklist"
    ],
    "updatedAt": "2026-05-07"
  },
  {
    "birdId": "euroys1",
    "chineseName": "蠣鸻",
    "englishName": "蠣鴴",
    "scientificName": "Haematopus ostralegus",
    "aliases": [],
    "order": {
      "zh": "鸻形目",
      "en": "Charadriiformes"
    },
    "family": {
      "zh": "Oystercatchers",
      "en": "Oystercatchers"
    },
    "dataLevel": "C",
    "sourceRefs": [
      "eBird API v2 taxonomy",
      "eBird CN-13 Hebei checklist"
    ],
    "updatedAt": "2026-05-07"
  },
  {
    "birdId": "slbgul1",
    "chineseName": "細嘴鸥",
    "englishName": "細嘴鷗",
    "scientificName": "Chroicocephalus genei",
    "aliases": [],
    "order": {
      "zh": "鸻形目",
      "en": "Charadriiformes"
    },
    "family": {
      "zh": "Gulls, Terns, and Skimmers",
      "en": "Gulls, Terns, and Skimmers"
    },
    "dataLevel": "C",
    "sourceRefs": [
      "eBird API v2 taxonomy",
      "eBird CN-13 Hebei checklist"
    ],
    "updatedAt": "2026-05-07"
  },
  {
    "birdId": "bkhgul",
    "chineseName": "红嘴鸥",
    "englishName": "紅嘴鷗",
    "scientificName": "Chroicocephalus ridibundus",
    "aliases": [],
    "order": {
      "zh": "鸻形目",
      "en": "Charadriiformes"
    },
    "family": {
      "zh": "Gulls, Terns, and Skimmers",
      "en": "Gulls, Terns, and Skimmers"
    },
    "dataLevel": "C",
    "sourceRefs": [
      "eBird API v2 taxonomy",
      "eBird CN-13 Hebei checklist"
    ],
    "updatedAt": "2026-05-07"
  },
  {
    "birdId": "litsti",
    "chineseName": "小滨鹬",
    "englishName": "小濱鷸",
    "scientificName": "Calidris minuta",
    "aliases": [],
    "order": {
      "zh": "鸻形目",
      "en": "Charadriiformes"
    },
    "family": {
      "zh": "Sandpipers and Allies",
      "en": "Sandpipers and Allies"
    },
    "dataLevel": "C",
    "sourceRefs": [
      "eBird API v2 taxonomy",
      "eBird CN-13 Hebei checklist"
    ],
    "updatedAt": "2026-05-07"
  },
  {
    "birdId": "casgul4",
    "chineseName": "蒙古银鸥",
    "englishName": "蒙古銀鷗",
    "scientificName": "Larus mongolicus",
    "aliases": [],
    "order": {
      "zh": "鸻形目",
      "en": "Charadriiformes"
    },
    "family": {
      "zh": "Gulls, Terns, and Skimmers",
      "en": "Gulls, Terns, and Skimmers"
    },
    "dataLevel": "C",
    "sourceRefs": [
      "eBird API v2 taxonomy",
      "eBird CN-13 Hebei checklist"
    ],
    "updatedAt": "2026-05-07"
  },
  {
    "birdId": "whiter2",
    "chineseName": "黑腹燕鸥",
    "englishName": "黑腹燕鷗",
    "scientificName": "Chlidonias hybrida",
    "aliases": [],
    "order": {
      "zh": "鸻形目",
      "en": "Charadriiformes"
    },
    "family": {
      "zh": "Gulls, Terns, and Skimmers",
      "en": "Gulls, Terns, and Skimmers"
    },
    "dataLevel": "C",
    "sourceRefs": [
      "eBird API v2 taxonomy",
      "eBird CN-13 Hebei checklist"
    ],
    "updatedAt": "2026-05-07"
  },
  {
    "birdId": "renpha",
    "chineseName": "红领瓣足鹬",
    "englishName": "紅領瓣足鷸",
    "scientificName": "Phalaropus lobatus",
    "aliases": [],
    "order": {
      "zh": "鸻形目",
      "en": "Charadriiformes"
    },
    "family": {
      "zh": "Sandpipers and Allies",
      "en": "Sandpipers and Allies"
    },
    "dataLevel": "C",
    "sourceRefs": [
      "eBird API v2 taxonomy",
      "eBird CN-13 Hebei checklist"
    ],
    "updatedAt": "2026-05-07"
  },
  {
    "birdId": "lobplo1",
    "chineseName": "劍鸻",
    "englishName": "劍鴴",
    "scientificName": "Thinornis placidus",
    "aliases": [],
    "order": {
      "zh": "鸻形目",
      "en": "Charadriiformes"
    },
    "family": {
      "zh": "Plovers and Lapwings",
      "en": "Plovers and Lapwings"
    },
    "dataLevel": "C",
    "sourceRefs": [
      "eBird API v2 taxonomy",
      "eBird CN-13 Hebei checklist"
    ],
    "updatedAt": "2026-05-07"
  },
  {
    "birdId": "grnsan",
    "chineseName": "白腰草鹬",
    "englishName": "白腰草鷸",
    "scientificName": "Tringa ochropus",
    "aliases": [],
    "order": {
      "zh": "鸻形目",
      "en": "Charadriiformes"
    },
    "family": {
      "zh": "Sandpipers and Allies",
      "en": "Sandpipers and Allies"
    },
    "dataLevel": "C",
    "sourceRefs": [
      "eBird API v2 taxonomy",
      "eBird CN-13 Hebei checklist"
    ],
    "updatedAt": "2026-05-07"
  },
  {
    "birdId": "oriplo1",
    "chineseName": "東方红胸鸻",
    "englishName": "東方紅胸鴴",
    "scientificName": "Anarhynchus veredus",
    "aliases": [],
    "order": {
      "zh": "鸻形目",
      "en": "Charadriiformes"
    },
    "family": {
      "zh": "Plovers and Lapwings",
      "en": "Plovers and Lapwings"
    },
    "dataLevel": "C",
    "sourceRefs": [
      "eBird API v2 taxonomy",
      "eBird CN-13 Hebei checklist"
    ],
    "updatedAt": "2026-05-07"
  },
  {
    "birdId": "jacsni",
    "chineseName": "小鹬",
    "englishName": "小鷸",
    "scientificName": "Lymnocryptes minimus",
    "aliases": [],
    "order": {
      "zh": "鸻形目",
      "en": "Charadriiformes"
    },
    "family": {
      "zh": "Sandpipers and Allies",
      "en": "Sandpipers and Allies"
    },
    "dataLevel": "C",
    "sourceRefs": [
      "eBird API v2 taxonomy",
      "eBird CN-13 Hebei checklist"
    ],
    "updatedAt": "2026-05-07"
  },
  {
    "birdId": "comsni",
    "chineseName": "田鹬",
    "englishName": "田鷸",
    "scientificName": "Gallinago gallinago",
    "aliases": [],
    "order": {
      "zh": "鸻形目",
      "en": "Charadriiformes"
    },
    "family": {
      "zh": "Sandpipers and Allies",
      "en": "Sandpipers and Allies"
    },
    "dataLevel": "C",
    "sourceRefs": [
      "eBird API v2 taxonomy",
      "eBird CN-13 Hebei checklist"
    ],
    "updatedAt": "2026-05-07"
  },
  {
    "birdId": "saugul2",
    "chineseName": "黑嘴鸥",
    "englishName": "黑嘴鷗",
    "scientificName": "Saundersilarus saundersi",
    "aliases": [],
    "order": {
      "zh": "鸻形目",
      "en": "Charadriiformes"
    },
    "family": {
      "zh": "Gulls, Terns, and Skimmers",
      "en": "Gulls, Terns, and Skimmers"
    },
    "dataLevel": "C",
    "sourceRefs": [
      "eBird API v2 taxonomy",
      "eBird CN-13 Hebei checklist"
    ],
    "updatedAt": "2026-05-07"
  },
  {
    "birdId": "gbhgul2",
    "chineseName": "漁鸥",
    "englishName": "漁鷗",
    "scientificName": "Ichthyaetus ichthyaetus",
    "aliases": [],
    "order": {
      "zh": "鸻形目",
      "en": "Charadriiformes"
    },
    "family": {
      "zh": "Gulls, Terns, and Skimmers",
      "en": "Gulls, Terns, and Skimmers"
    },
    "dataLevel": "C",
    "sourceRefs": [
      "eBird API v2 taxonomy",
      "eBird CN-13 Hebei checklist"
    ],
    "updatedAt": "2026-05-07"
  },
  {
    "birdId": "mewgul",
    "chineseName": "歐亞海鸥",
    "englishName": "歐亞海鷗",
    "scientificName": "Larus canus",
    "aliases": [],
    "order": {
      "zh": "鸻形目",
      "en": "Charadriiformes"
    },
    "family": {
      "zh": "Gulls, Terns, and Skimmers",
      "en": "Gulls, Terns, and Skimmers"
    },
    "dataLevel": "C",
    "sourceRefs": [
      "eBird API v2 taxonomy",
      "eBird CN-13 Hebei checklist"
    ],
    "updatedAt": "2026-05-07"
  },
  {
    "birdId": "veggul1",
    "chineseName": "西伯利亞银鸥",
    "englishName": "西伯利亞銀鷗",
    "scientificName": "Larus vegae",
    "aliases": [],
    "order": {
      "zh": "鸻形目",
      "en": "Charadriiformes"
    },
    "family": {
      "zh": "Gulls, Terns, and Skimmers",
      "en": "Gulls, Terns, and Skimmers"
    },
    "dataLevel": "C",
    "sourceRefs": [
      "eBird API v2 taxonomy",
      "eBird CN-13 Hebei checklist"
    ],
    "updatedAt": "2026-05-07"
  },
  {
    "birdId": "pomjae",
    "chineseName": "中賊鸥",
    "englishName": "中賊鷗",
    "scientificName": "Stercorarius pomarinus",
    "aliases": [],
    "order": {
      "zh": "鸻形目",
      "en": "Charadriiformes"
    },
    "family": {
      "zh": "Skuas and Jaegers",
      "en": "Skuas and Jaegers"
    },
    "dataLevel": "C",
    "sourceRefs": [
      "eBird API v2 taxonomy",
      "eBird CN-13 Hebei checklist"
    ],
    "updatedAt": "2026-05-07"
  },
  {
    "birdId": "gubter2",
    "chineseName": "鸥嘴燕鸥",
    "englishName": "鷗嘴燕鷗",
    "scientificName": "Gelochelidon nilotica",
    "aliases": [],
    "order": {
      "zh": "鸻形目",
      "en": "Charadriiformes"
    },
    "family": {
      "zh": "Gulls, Terns, and Skimmers",
      "en": "Gulls, Terns, and Skimmers"
    },
    "dataLevel": "C",
    "sourceRefs": [
      "eBird API v2 taxonomy",
      "eBird CN-13 Hebei checklist"
    ],
    "updatedAt": "2026-05-07"
  },
  {
    "birdId": "litter1",
    "chineseName": "小燕鸥",
    "englishName": "小燕鷗",
    "scientificName": "Sternula albifrons",
    "aliases": [],
    "order": {
      "zh": "鸻形目",
      "en": "Charadriiformes"
    },
    "family": {
      "zh": "Gulls, Terns, and Skimmers",
      "en": "Gulls, Terns, and Skimmers"
    },
    "dataLevel": "C",
    "sourceRefs": [
      "eBird API v2 taxonomy",
      "eBird CN-13 Hebei checklist"
    ],
    "updatedAt": "2026-05-07"
  },
  {
    "birdId": "comter",
    "chineseName": "燕鸥",
    "englishName": "燕鷗",
    "scientificName": "Sterna hirundo",
    "aliases": [],
    "order": {
      "zh": "鸻形目",
      "en": "Charadriiformes"
    },
    "family": {
      "zh": "Gulls, Terns, and Skimmers",
      "en": "Gulls, Terns, and Skimmers"
    },
    "dataLevel": "C",
    "sourceRefs": [
      "eBird API v2 taxonomy",
      "eBird CN-13 Hebei checklist"
    ],
    "updatedAt": "2026-05-07"
  },
  {
    "birdId": "sander",
    "chineseName": "三趾滨鹬",
    "englishName": "三趾濱鷸",
    "scientificName": "Calidris alba",
    "aliases": [],
    "order": {
      "zh": "鸻形目",
      "en": "Charadriiformes"
    },
    "family": {
      "zh": "Sandpipers and Allies",
      "en": "Sandpipers and Allies"
    },
    "dataLevel": "C",
    "sourceRefs": [
      "eBird API v2 taxonomy",
      "eBird CN-13 Hebei checklist"
    ],
    "updatedAt": "2026-05-07"
  },
  {
    "birdId": "relgul2",
    "chineseName": "遺鸥",
    "englishName": "遺鷗",
    "scientificName": "Ichthyaetus relictus",
    "aliases": [],
    "order": {
      "zh": "鸻形目",
      "en": "Charadriiformes"
    },
    "family": {
      "zh": "Gulls, Terns, and Skimmers",
      "en": "Gulls, Terns, and Skimmers"
    },
    "dataLevel": "C",
    "sourceRefs": [
      "eBird API v2 taxonomy",
      "eBird CN-13 Hebei checklist"
    ],
    "updatedAt": "2026-05-07"
  },
  {
    "birdId": "ruff",
    "chineseName": "流蘇鹬",
    "englishName": "流蘇鷸",
    "scientificName": "Calidris pugnax",
    "aliases": [],
    "order": {
      "zh": "鸻形目",
      "en": "Charadriiformes"
    },
    "family": {
      "zh": "Sandpipers and Allies",
      "en": "Sandpipers and Allies"
    },
    "dataLevel": "C",
    "sourceRefs": [
      "eBird API v2 taxonomy",
      "eBird CN-13 Hebei checklist"
    ],
    "updatedAt": "2026-05-07"
  },
  {
    "birdId": "babcra1",
    "chineseName": "斑脇秧雞",
    "englishName": "斑脇秧雞",
    "scientificName": "Zapornia paykullii",
    "aliases": [],
    "order": {
      "zh": "鹤形目",
      "en": "Gruiformes"
    },
    "family": {
      "zh": "Rails, Gallinules, and Coots",
      "en": "Rails, Gallinules, and Coots"
    },
    "dataLevel": "C",
    "sourceRefs": [
      "eBird API v2 taxonomy",
      "eBird CN-13 Hebei checklist"
    ],
    "updatedAt": "2026-05-07"
  },
  {
    "birdId": "baepoc1",
    "chineseName": "青头潛鸭",
    "englishName": "青頭潛鴨",
    "scientificName": "Aythya baeri",
    "aliases": [],
    "order": {
      "zh": "雁形目",
      "en": "Anseriformes"
    },
    "family": {
      "zh": "Ducks, Geese, and Waterfowl",
      "en": "Ducks, Geese, and Waterfowl"
    },
    "dataLevel": "C",
    "sourceRefs": [
      "eBird API v2 taxonomy",
      "eBird CN-13 Hebei checklist"
    ],
    "updatedAt": "2026-05-07"
  },
  {
    "birdId": "bahgoo",
    "chineseName": "斑头雁",
    "englishName": "斑頭雁",
    "scientificName": "Anser indicus",
    "aliases": [],
    "order": {
      "zh": "雁形目",
      "en": "Anseriformes"
    },
    "family": {
      "zh": "Ducks, Geese, and Waterfowl",
      "en": "Ducks, Geese, and Waterfowl"
    },
    "dataLevel": "C",
    "sourceRefs": [
      "eBird API v2 taxonomy",
      "eBird CN-13 Hebei checklist"
    ],
    "updatedAt": "2026-05-07"
  },
  {
    "birdId": "baicra1",
    "chineseName": "小秧雞",
    "englishName": "小秧雞",
    "scientificName": "Zapornia pusilla",
    "aliases": [],
    "order": {
      "zh": "鹤形目",
      "en": "Gruiformes"
    },
    "family": {
      "zh": "Rails, Gallinules, and Coots",
      "en": "Rails, Gallinules, and Coots"
    },
    "dataLevel": "C",
    "sourceRefs": [
      "eBird API v2 taxonomy",
      "eBird CN-13 Hebei checklist"
    ],
    "updatedAt": "2026-05-07"
  },
  {
    "birdId": "baitea",
    "chineseName": "巴鸭",
    "englishName": "巴鴨",
    "scientificName": "Sibirionetta formosa",
    "aliases": [],
    "order": {
      "zh": "雁形目",
      "en": "Anseriformes"
    },
    "family": {
      "zh": "Ducks, Geese, and Waterfowl",
      "en": "Ducks, Geese, and Waterfowl"
    },
    "dataLevel": "C",
    "sourceRefs": [
      "eBird API v2 taxonomy",
      "eBird CN-13 Hebei checklist"
    ],
    "updatedAt": "2026-05-07"
  },
  {
    "birdId": "bcnher",
    "chineseName": "夜鹭",
    "englishName": "夜鷺",
    "scientificName": "Nycticorax nycticorax",
    "aliases": [],
    "order": {
      "zh": "鹈形目",
      "en": "Pelecaniformes"
    },
    "family": {
      "zh": "Herons, Egrets, and Bitterns",
      "en": "Herons, Egrets, and Bitterns"
    },
    "dataLevel": "C",
    "sourceRefs": [
      "eBird API v2 taxonomy",
      "eBird CN-13 Hebei checklist"
    ],
    "updatedAt": "2026-05-07"
  },
  {
    "birdId": "besra1",
    "chineseName": "松雀鷹",
    "englishName": "松雀鷹",
    "scientificName": "Tachyspiza virgata",
    "aliases": [],
    "order": {
      "zh": "鹰形目",
      "en": "Accipitriformes"
    },
    "family": {
      "zh": "Hawks, Eagles, and Kites",
      "en": "Hawks, Eagles, and Kites"
    },
    "dataLevel": "C",
    "sourceRefs": [
      "eBird API v2 taxonomy",
      "eBird CN-13 Hebei checklist"
    ],
    "updatedAt": "2026-05-07"
  },
  {
    "birdId": "bkskit1",
    "chineseName": "黑翅鸢",
    "englishName": "黑翅鳶",
    "scientificName": "Elanus caeruleus",
    "aliases": [],
    "order": {
      "zh": "鹰形目",
      "en": "Accipitriformes"
    },
    "family": {
      "zh": "Hawks, Eagles, and Kites",
      "en": "Hawks, Eagles, and Kites"
    },
    "dataLevel": "C",
    "sourceRefs": [
      "eBird API v2 taxonomy",
      "eBird CN-13 Hebei checklist"
    ],
    "updatedAt": "2026-05-07"
  },
  {
    "birdId": "blabaz1",
    "chineseName": "黑冠鵑隼",
    "englishName": "黑冠鵑隼",
    "scientificName": "Aviceda leuphotes",
    "aliases": [],
    "order": {
      "zh": "鹰形目",
      "en": "Accipitriformes"
    },
    "family": {
      "zh": "Hawks, Eagles, and Kites",
      "en": "Hawks, Eagles, and Kites"
    },
    "dataLevel": "C",
    "sourceRefs": [
      "eBird API v2 taxonomy",
      "eBird CN-13 Hebei checklist"
    ],
    "updatedAt": "2026-05-07"
  },
  {
    "birdId": "blabit1",
    "chineseName": "黄颈黑鹭",
    "englishName": "黃頸黑鷺",
    "scientificName": "Botaurus flavicollis",
    "aliases": [],
    "order": {
      "zh": "鹈形目",
      "en": "Pelecaniformes"
    },
    "family": {
      "zh": "Herons, Egrets, and Bitterns",
      "en": "Herons, Egrets, and Bitterns"
    },
    "dataLevel": "C",
    "sourceRefs": [
      "eBird API v2 taxonomy",
      "eBird CN-13 Hebei checklist"
    ],
    "updatedAt": "2026-05-07"
  },
  {
    "birdId": "blakit1",
    "chineseName": "黑鸢",
    "englishName": "黑鳶",
    "scientificName": "Milvus migrans",
    "aliases": [],
    "order": {
      "zh": "鹰形目",
      "en": "Accipitriformes"
    },
    "family": {
      "zh": "Hawks, Eagles, and Kites",
      "en": "Hawks, Eagles, and Kites"
    },
    "dataLevel": "C",
    "sourceRefs": [
      "eBird API v2 taxonomy",
      "eBird CN-13 Hebei checklist"
    ],
    "updatedAt": "2026-05-07"
  },
  {
    "birdId": "blfspo1",
    "chineseName": "黑面琵鹭",
    "englishName": "黑面琵鷺",
    "scientificName": "Platalea minor",
    "aliases": [],
    "order": {
      "zh": "鹈形目",
      "en": "Pelecaniformes"
    },
    "family": {
      "zh": "Ibises and Spoonbills",
      "en": "Ibises and Spoonbills"
    },
    "dataLevel": "C",
    "sourceRefs": [
      "eBird API v2 taxonomy",
      "eBird CN-13 Hebei checklist"
    ],
    "updatedAt": "2026-05-07"
  },
  {
    "birdId": "blhibi1",
    "chineseName": "黑头白䴉",
    "englishName": "黑頭白䴉",
    "scientificName": "Threskiornis melanocephalus",
    "aliases": [],
    "order": {
      "zh": "鹈形目",
      "en": "Pelecaniformes"
    },
    "family": {
      "zh": "Ibises and Spoonbills",
      "en": "Ibises and Spoonbills"
    },
    "dataLevel": "C",
    "sourceRefs": [
      "eBird API v2 taxonomy",
      "eBird CN-13 Hebei checklist"
    ],
    "updatedAt": "2026-05-07"
  },
  {
    "birdId": "blkswa",
    "chineseName": "黑天鵝",
    "englishName": "黑天鵝",
    "scientificName": "Cygnus atratus",
    "aliases": [],
    "order": {
      "zh": "雁形目",
      "en": "Anseriformes"
    },
    "family": {
      "zh": "Ducks, Geese, and Waterfowl",
      "en": "Ducks, Geese, and Waterfowl"
    },
    "dataLevel": "C",
    "sourceRefs": [
      "eBird API v2 taxonomy",
      "eBird CN-13 Hebei checklist"
    ],
    "updatedAt": "2026-05-07"
  },
  {
    "birdId": "bncrai1",
    "chineseName": "东亚秧雞",
    "englishName": "東亞秧雞",
    "scientificName": "Rallus indicus",
    "aliases": [],
    "order": {
      "zh": "鹤形目",
      "en": "Gruiformes"
    },
    "family": {
      "zh": "Rails, Gallinules, and Coots",
      "en": "Rails, Gallinules, and Coots"
    },
    "dataLevel": "C",
    "sourceRefs": [
      "eBird API v2 taxonomy",
      "eBird CN-13 Hebei checklist"
    ],
    "updatedAt": "2026-05-07"
  },
  {
    "birdId": "booeag1",
    "chineseName": "靴隼鵰",
    "englishName": "靴隼鵰",
    "scientificName": "Hieraaetus pennatus",
    "aliases": [],
    "order": {
      "zh": "鹰形目",
      "en": "Accipitriformes"
    },
    "family": {
      "zh": "Hawks, Eagles, and Kites",
      "en": "Hawks, Eagles, and Kites"
    },
    "dataLevel": "C",
    "sourceRefs": [
      "eBird API v2 taxonomy",
      "eBird CN-13 Hebei checklist"
    ],
    "updatedAt": "2026-05-07"
  },
  {
    "birdId": "brant",
    "chineseName": "黑雁",
    "englishName": "黑雁",
    "scientificName": "Branta bernicla",
    "aliases": [],
    "order": {
      "zh": "雁形目",
      "en": "Anseriformes"
    },
    "family": {
      "zh": "Ducks, Geese, and Waterfowl",
      "en": "Ducks, Geese, and Waterfowl"
    },
    "dataLevel": "C",
    "sourceRefs": [
      "eBird API v2 taxonomy",
      "eBird CN-13 Hebei checklist"
    ],
    "updatedAt": "2026-05-07"
  },
  {
    "birdId": "categr2",
    "chineseName": "黄头鹭",
    "englishName": "黃頭鷺",
    "scientificName": "Ardea coromanda",
    "aliases": [],
    "order": {
      "zh": "鹈形目",
      "en": "Pelecaniformes"
    },
    "family": {
      "zh": "Herons, Egrets, and Bitterns",
      "en": "Herons, Egrets, and Bitterns"
    },
    "dataLevel": "C",
    "sourceRefs": [
      "eBird API v2 taxonomy",
      "eBird CN-13 Hebei checklist"
    ],
    "updatedAt": "2026-05-07"
  },
  {
    "birdId": "chiegr",
    "chineseName": "唐白鹭",
    "englishName": "唐白鷺",
    "scientificName": "Egretta eulophotes",
    "aliases": [],
    "order": {
      "zh": "鹈形目",
      "en": "Pelecaniformes"
    },
    "family": {
      "zh": "Herons, Egrets, and Bitterns",
      "en": "Herons, Egrets, and Bitterns"
    },
    "dataLevel": "C",
    "sourceRefs": [
      "eBird API v2 taxonomy",
      "eBird CN-13 Hebei checklist"
    ],
    "updatedAt": "2026-05-07"
  },
  {
    "birdId": "chpher1",
    "chineseName": "池鹭",
    "englishName": "池鷺",
    "scientificName": "Ardeola bacchus",
    "aliases": [],
    "order": {
      "zh": "鹈形目",
      "en": "Pelecaniformes"
    },
    "family": {
      "zh": "Herons, Egrets, and Bitterns",
      "en": "Herons, Egrets, and Bitterns"
    },
    "dataLevel": "C",
    "sourceRefs": [
      "eBird API v2 taxonomy",
      "eBird CN-13 Hebei checklist"
    ],
    "updatedAt": "2026-05-07"
  },
  {
    "birdId": "cinbit1",
    "chineseName": "栗小鹭",
    "englishName": "栗小鷺",
    "scientificName": "Botaurus cinnamomeus",
    "aliases": [],
    "order": {
      "zh": "鹈形目",
      "en": "Pelecaniformes"
    },
    "family": {
      "zh": "Herons, Egrets, and Bitterns",
      "en": "Herons, Egrets, and Bitterns"
    },
    "dataLevel": "C",
    "sourceRefs": [
      "eBird API v2 taxonomy",
      "eBird CN-13 Hebei checklist"
    ],
    "updatedAt": "2026-05-07"
  },
  {
    "birdId": "cinvul1",
    "chineseName": "禿鹫",
    "englishName": "禿鷲",
    "scientificName": "Aegypius monachus",
    "aliases": [],
    "order": {
      "zh": "鹰形目",
      "en": "Accipitriformes"
    },
    "family": {
      "zh": "Hawks, Eagles, and Kites",
      "en": "Hawks, Eagles, and Kites"
    },
    "dataLevel": "C",
    "sourceRefs": [
      "eBird API v2 taxonomy",
      "eBird CN-13 Hebei checklist"
    ],
    "updatedAt": "2026-05-07"
  },
  {
    "birdId": "combuz6",
    "chineseName": "东方𫛭",
    "englishName": "東方鵟",
    "scientificName": "Buteo japonicus",
    "aliases": [],
    "order": {
      "zh": "鹰形目",
      "en": "Accipitriformes"
    },
    "family": {
      "zh": "Hawks, Eagles, and Kites",
      "en": "Hawks, Eagles, and Kites"
    },
    "dataLevel": "C",
    "sourceRefs": [
      "eBird API v2 taxonomy",
      "eBird CN-13 Hebei checklist"
    ],
    "updatedAt": "2026-05-07"
  },
  {
    "birdId": "comcra",
    "chineseName": "灰鹤",
    "englishName": "灰鶴",
    "scientificName": "Grus grus",
    "aliases": [],
    "order": {
      "zh": "鹤形目",
      "en": "Gruiformes"
    },
    "family": {
      "zh": "Cranes",
      "en": "Cranes"
    },
    "dataLevel": "C",
    "sourceRefs": [
      "eBird API v2 taxonomy",
      "eBird CN-13 Hebei checklist"
    ],
    "updatedAt": "2026-05-07"
  },
  {
    "birdId": "comgol",
    "chineseName": "鹊鸭",
    "englishName": "鵲鴨",
    "scientificName": "Bucephala clangula",
    "aliases": [],
    "order": {
      "zh": "雁形目",
      "en": "Anseriformes"
    },
    "family": {
      "zh": "Ducks, Geese, and Waterfowl",
      "en": "Ducks, Geese, and Waterfowl"
    },
    "dataLevel": "C",
    "sourceRefs": [
      "eBird API v2 taxonomy",
      "eBird CN-13 Hebei checklist"
    ],
    "updatedAt": "2026-05-07"
  },
  {
    "birdId": "commer",
    "chineseName": "川秋沙",
    "englishName": "川秋沙",
    "scientificName": "Mergus merganser",
    "aliases": [],
    "order": {
      "zh": "雁形目",
      "en": "Anseriformes"
    },
    "family": {
      "zh": "Ducks, Geese, and Waterfowl",
      "en": "Ducks, Geese, and Waterfowl"
    },
    "dataLevel": "C",
    "sourceRefs": [
      "eBird API v2 taxonomy",
      "eBird CN-13 Hebei checklist"
    ],
    "updatedAt": "2026-05-07"
  },
  {
    "birdId": "commoo3",
    "chineseName": "红冠水雞",
    "englishName": "紅冠水雞",
    "scientificName": "Gallinula chloropus",
    "aliases": [],
    "order": {
      "zh": "鹤形目",
      "en": "Gruiformes"
    },
    "family": {
      "zh": "Rails, Gallinules, and Coots",
      "en": "Rails, Gallinules, and Coots"
    },
    "dataLevel": "C",
    "sourceRefs": [
      "eBird API v2 taxonomy",
      "eBird CN-13 Hebei checklist"
    ],
    "updatedAt": "2026-05-07"
  },
  {
    "birdId": "compoc",
    "chineseName": "红头潛鸭",
    "englishName": "紅頭潛鴨",
    "scientificName": "Aythya ferina",
    "aliases": [],
    "order": {
      "zh": "雁形目",
      "en": "Anseriformes"
    },
    "family": {
      "zh": "Ducks, Geese, and Waterfowl",
      "en": "Ducks, Geese, and Waterfowl"
    },
    "dataLevel": "C",
    "sourceRefs": [
      "eBird API v2 taxonomy",
      "eBird CN-13 Hebei checklist"
    ],
    "updatedAt": "2026-05-07"
  },
  {
    "birdId": "comshe",
    "chineseName": "花凫",
    "englishName": "花鳧",
    "scientificName": "Tadorna tadorna",
    "aliases": [],
    "order": {
      "zh": "雁形目",
      "en": "Anseriformes"
    },
    "family": {
      "zh": "Ducks, Geese, and Waterfowl",
      "en": "Ducks, Geese, and Waterfowl"
    },
    "dataLevel": "C",
    "sourceRefs": [
      "eBird API v2 taxonomy",
      "eBird CN-13 Hebei checklist"
    ],
    "updatedAt": "2026-05-07"
  },
  {
    "birdId": "copgoo1",
    "chineseName": "棉鸭",
    "englishName": "棉鴨",
    "scientificName": "Nettapus coromandelianus",
    "aliases": [],
    "order": {
      "zh": "雁形目",
      "en": "Anseriformes"
    },
    "family": {
      "zh": "Ducks, Geese, and Waterfowl",
      "en": "Ducks, Geese, and Waterfowl"
    },
    "dataLevel": "C",
    "sourceRefs": [
      "eBird API v2 taxonomy",
      "eBird CN-13 Hebei checklist"
    ],
    "updatedAt": "2026-05-07"
  },
  {
    "birdId": "cregos1",
    "chineseName": "凤头蒼鷹",
    "englishName": "鳳頭蒼鷹",
    "scientificName": "Lophospiza trivirgata",
    "aliases": [],
    "order": {
      "zh": "鹰形目",
      "en": "Accipitriformes"
    },
    "family": {
      "zh": "Hawks, Eagles, and Kites",
      "en": "Hawks, Eagles, and Kites"
    },
    "dataLevel": "C",
    "sourceRefs": [
      "eBird API v2 taxonomy",
      "eBird CN-13 Hebei checklist"
    ],
    "updatedAt": "2026-05-07"
  },
  {
    "birdId": "dalpel1",
    "chineseName": "卷羽鵜鶘",
    "englishName": "卷羽鵜鶘",
    "scientificName": "Pelecanus crispus",
    "aliases": [],
    "order": {
      "zh": "鹈形目",
      "en": "Pelecaniformes"
    },
    "family": {
      "zh": "Pelicans",
      "en": "Pelicans"
    },
    "dataLevel": "C",
    "sourceRefs": [
      "eBird API v2 taxonomy",
      "eBird CN-13 Hebei checklist"
    ],
    "updatedAt": "2026-05-07"
  },
  {
    "birdId": "demcra1",
    "chineseName": "簑羽鹤",
    "englishName": "簑羽鶴",
    "scientificName": "Grus virgo",
    "aliases": [],
    "order": {
      "zh": "鹤形目",
      "en": "Gruiformes"
    },
    "family": {
      "zh": "Cranes",
      "en": "Cranes"
    },
    "dataLevel": "C",
    "sourceRefs": [
      "eBird API v2 taxonomy",
      "eBird CN-13 Hebei checklist"
    ],
    "updatedAt": "2026-05-07"
  },
  {
    "birdId": "eargre",
    "chineseName": "黑颈䴙䴘",
    "englishName": "黑頸鸊鷉",
    "scientificName": "Podiceps nigricollis",
    "aliases": [],
    "order": {
      "zh": "䴙䴘目",
      "en": "Podicipediformes"
    },
    "family": {
      "zh": "Grebes",
      "en": "Grebes"
    },
    "dataLevel": "C",
    "sourceRefs": [
      "eBird API v2 taxonomy",
      "eBird CN-13 Hebei checklist"
    ],
    "updatedAt": "2026-05-07"
  },
  {
    "birdId": "easmah1",
    "chineseName": "东方泽𫛭",
    "englishName": "東方澤鵟",
    "scientificName": "Circus spilonotus",
    "aliases": [],
    "order": {
      "zh": "鹰形目",
      "en": "Accipitriformes"
    },
    "family": {
      "zh": "Hawks, Eagles, and Kites",
      "en": "Hawks, Eagles, and Kites"
    },
    "dataLevel": "C",
    "sourceRefs": [
      "eBird API v2 taxonomy",
      "eBird CN-13 Hebei checklist"
    ],
    "updatedAt": "2026-05-07"
  },
  {
    "birdId": "eurcoo",
    "chineseName": "白冠雞",
    "englishName": "白冠雞",
    "scientificName": "Fulica atra",
    "aliases": [],
    "order": {
      "zh": "鹤形目",
      "en": "Gruiformes"
    },
    "family": {
      "zh": "Rails, Gallinules, and Coots",
      "en": "Rails, Gallinules, and Coots"
    },
    "dataLevel": "C",
    "sourceRefs": [
      "eBird API v2 taxonomy",
      "eBird CN-13 Hebei checklist"
    ],
    "updatedAt": "2026-05-07"
  },
  {
    "birdId": "eurspa1",
    "chineseName": "北雀鷹",
    "englishName": "北雀鷹",
    "scientificName": "Accipiter nisus",
    "aliases": [],
    "order": {
      "zh": "鹰形目",
      "en": "Accipitriformes"
    },
    "family": {
      "zh": "Hawks, Eagles, and Kites",
      "en": "Hawks, Eagles, and Kites"
    },
    "dataLevel": "C",
    "sourceRefs": [
      "eBird API v2 taxonomy",
      "eBird CN-13 Hebei checklist"
    ],
    "updatedAt": "2026-05-07"
  },
  {
    "birdId": "eurspo1",
    "chineseName": "白琵鹭",
    "englishName": "白琵鷺",
    "scientificName": "Platalea leucorodia",
    "aliases": [],
    "order": {
      "zh": "鹈形目",
      "en": "Pelecaniformes"
    },
    "family": {
      "zh": "Ibises and Spoonbills",
      "en": "Ibises and Spoonbills"
    },
    "dataLevel": "C",
    "sourceRefs": [
      "eBird API v2 taxonomy",
      "eBird CN-13 Hebei checklist"
    ],
    "updatedAt": "2026-05-07"
  },
  {
    "birdId": "eurwig",
    "chineseName": "赤颈鸭",
    "englishName": "赤頸鴨",
    "scientificName": "Mareca penelope",
    "aliases": [],
    "order": {
      "zh": "雁形目",
      "en": "Anseriformes"
    },
    "family": {
      "zh": "Ducks, Geese, and Waterfowl",
      "en": "Ducks, Geese, and Waterfowl"
    },
    "dataLevel": "C",
    "sourceRefs": [
      "eBird API v2 taxonomy",
      "eBird CN-13 Hebei checklist"
    ],
    "updatedAt": "2026-05-07"
  },
  {
    "birdId": "falduc",
    "chineseName": "罗文鸭",
    "englishName": "羅文鴨",
    "scientificName": "Mareca falcata",
    "aliases": [],
    "order": {
      "zh": "雁形目",
      "en": "Anseriformes"
    },
    "family": {
      "zh": "Ducks, Geese, and Waterfowl",
      "en": "Ducks, Geese, and Waterfowl"
    },
    "dataLevel": "C",
    "sourceRefs": [
      "eBird API v2 taxonomy",
      "eBird CN-13 Hebei checklist"
    ],
    "updatedAt": "2026-05-07"
  },
  {
    "birdId": "ferduc",
    "chineseName": "白眼潛鸭",
    "englishName": "白眼潛鴨",
    "scientificName": "Aythya nyroca",
    "aliases": [],
    "order": {
      "zh": "雁形目",
      "en": "Anseriformes"
    },
    "family": {
      "zh": "Ducks, Geese, and Waterfowl",
      "en": "Ducks, Geese, and Waterfowl"
    },
    "dataLevel": "C",
    "sourceRefs": [
      "eBird API v2 taxonomy",
      "eBird CN-13 Hebei checklist"
    ],
    "updatedAt": "2026-05-07"
  },
  {
    "birdId": "gadwal",
    "chineseName": "赤膀鸭",
    "englishName": "赤膀鴨",
    "scientificName": "Mareca strepera",
    "aliases": [],
    "order": {
      "zh": "雁形目",
      "en": "Anseriformes"
    },
    "family": {
      "zh": "Ducks, Geese, and Waterfowl",
      "en": "Ducks, Geese, and Waterfowl"
    },
    "dataLevel": "C",
    "sourceRefs": [
      "eBird API v2 taxonomy",
      "eBird CN-13 Hebei checklist"
    ],
    "updatedAt": "2026-05-07"
  },
  {
    "birdId": "gargan",
    "chineseName": "白眉鸭",
    "englishName": "白眉鴨",
    "scientificName": "Spatula querquedula",
    "aliases": [],
    "order": {
      "zh": "雁形目",
      "en": "Anseriformes"
    },
    "family": {
      "zh": "Ducks, Geese, and Waterfowl",
      "en": "Ducks, Geese, and Waterfowl"
    },
    "dataLevel": "C",
    "sourceRefs": [
      "eBird API v2 taxonomy",
      "eBird CN-13 Hebei checklist"
    ],
    "updatedAt": "2026-05-07"
  },
  {
    "birdId": "gnwtea",
    "chineseName": "小水鸭",
    "englishName": "小水鴨",
    "scientificName": "Anas crecca",
    "aliases": [],
    "order": {
      "zh": "雁形目",
      "en": "Anseriformes"
    },
    "family": {
      "zh": "Ducks, Geese, and Waterfowl",
      "en": "Ducks, Geese, and Waterfowl"
    },
    "dataLevel": "C",
    "sourceRefs": [
      "eBird API v2 taxonomy",
      "eBird CN-13 Hebei checklist"
    ],
    "updatedAt": "2026-05-07"
  },
  {
    "birdId": "goleag",
    "chineseName": "金鵰",
    "englishName": "金鵰",
    "scientificName": "Aquila chrysaetos",
    "aliases": [],
    "order": {
      "zh": "鹰形目",
      "en": "Accipitriformes"
    },
    "family": {
      "zh": "Hawks, Eagles, and Kites",
      "en": "Hawks, Eagles, and Kites"
    },
    "dataLevel": "C",
    "sourceRefs": [
      "eBird API v2 taxonomy",
      "eBird CN-13 Hebei checklist"
    ],
    "updatedAt": "2026-05-07"
  },
  {
    "birdId": "gragoo",
    "chineseName": "灰雁",
    "englishName": "灰雁",
    "scientificName": "Anser anser",
    "aliases": [],
    "order": {
      "zh": "雁形目",
      "en": "Anseriformes"
    },
    "family": {
      "zh": "Ducks, Geese, and Waterfowl",
      "en": "Ducks, Geese, and Waterfowl"
    },
    "dataLevel": "C",
    "sourceRefs": [
      "eBird API v2 taxonomy",
      "eBird CN-13 Hebei checklist"
    ],
    "updatedAt": "2026-05-07"
  },
  {
    "birdId": "graher1",
    "chineseName": "蒼鹭",
    "englishName": "蒼鷺",
    "scientificName": "Ardea cinerea",
    "aliases": [],
    "order": {
      "zh": "鹈形目",
      "en": "Pelecaniformes"
    },
    "family": {
      "zh": "Herons, Egrets, and Bitterns",
      "en": "Herons, Egrets, and Bitterns"
    },
    "dataLevel": "C",
    "sourceRefs": [
      "eBird API v2 taxonomy",
      "eBird CN-13 Hebei checklist"
    ],
    "updatedAt": "2026-05-07"
  },
  {
    "birdId": "grcgre1",
    "chineseName": "冠䴙䴘",
    "englishName": "冠鸊鷉",
    "scientificName": "Podiceps cristatus",
    "aliases": [],
    "order": {
      "zh": "䴙䴘目",
      "en": "Podicipediformes"
    },
    "family": {
      "zh": "Grebes",
      "en": "Grebes"
    },
    "dataLevel": "C",
    "sourceRefs": [
      "eBird API v2 taxonomy",
      "eBird CN-13 Hebei checklist"
    ],
    "updatedAt": "2026-05-07"
  },
  {
    "birdId": "grebit1",
    "chineseName": "大麻鹭",
    "englishName": "大麻鷺",
    "scientificName": "Botaurus stellaris",
    "aliases": [],
    "order": {
      "zh": "鹈形目",
      "en": "Pelecaniformes"
    },
    "family": {
      "zh": "Herons, Egrets, and Bitterns",
      "en": "Herons, Egrets, and Bitterns"
    },
    "dataLevel": "C",
    "sourceRefs": [
      "eBird API v2 taxonomy",
      "eBird CN-13 Hebei checklist"
    ],
    "updatedAt": "2026-05-07"
  },
  {
    "birdId": "greegr",
    "chineseName": "大白鹭",
    "englishName": "大白鷺",
    "scientificName": "Ardea alba",
    "aliases": [],
    "order": {
      "zh": "鹈形目",
      "en": "Pelecaniformes"
    },
    "family": {
      "zh": "Herons, Egrets, and Bitterns",
      "en": "Herons, Egrets, and Bitterns"
    },
    "dataLevel": "C",
    "sourceRefs": [
      "eBird API v2 taxonomy",
      "eBird CN-13 Hebei checklist"
    ],
    "updatedAt": "2026-05-07"
  },
  {
    "birdId": "gresca",
    "chineseName": "斑背潛鸭",
    "englishName": "斑背潛鴨",
    "scientificName": "Aythya marila",
    "aliases": [],
    "order": {
      "zh": "雁形目",
      "en": "Anseriformes"
    },
    "family": {
      "zh": "Ducks, Geese, and Waterfowl",
      "en": "Ducks, Geese, and Waterfowl"
    },
    "dataLevel": "C",
    "sourceRefs": [
      "eBird API v2 taxonomy",
      "eBird CN-13 Hebei checklist"
    ],
    "updatedAt": "2026-05-07"
  },
  {
    "birdId": "grfhaw1",
    "chineseName": "赤腹鷹",
    "englishName": "赤腹鷹",
    "scientificName": "Tachyspiza soloensis",
    "aliases": [],
    "order": {
      "zh": "鹰形目",
      "en": "Accipitriformes"
    },
    "family": {
      "zh": "Hawks, Eagles, and Kites",
      "en": "Hawks, Eagles, and Kites"
    },
    "dataLevel": "C",
    "sourceRefs": [
      "eBird API v2 taxonomy",
      "eBird CN-13 Hebei checklist"
    ],
    "updatedAt": "2026-05-07"
  },
  {
    "birdId": "grseag1",
    "chineseName": "花鵰",
    "englishName": "花鵰",
    "scientificName": "Clanga clanga",
    "aliases": [],
    "order": {
      "zh": "鹰形目",
      "en": "Accipitriformes"
    },
    "family": {
      "zh": "Hawks, Eagles, and Kites",
      "en": "Hawks, Eagles, and Kites"
    },
    "dataLevel": "C",
    "sourceRefs": [
      "eBird API v2 taxonomy",
      "eBird CN-13 Hebei checklist"
    ],
    "updatedAt": "2026-05-07"
  },
  {
    "birdId": "gwfgoo",
    "chineseName": "白額雁",
    "englishName": "白額雁",
    "scientificName": "Anser albifrons",
    "aliases": [],
    "order": {
      "zh": "雁形目",
      "en": "Anseriformes"
    },
    "family": {
      "zh": "Ducks, Geese, and Waterfowl",
      "en": "Ducks, Geese, and Waterfowl"
    },
    "dataLevel": "C",
    "sourceRefs": [
      "eBird API v2 taxonomy",
      "eBird CN-13 Hebei checklist"
    ],
    "updatedAt": "2026-05-07"
  },
  {
    "birdId": "gyfbuz1",
    "chineseName": "灰面𫛭鷹",
    "englishName": "灰面鵟鷹",
    "scientificName": "Butastur indicus",
    "aliases": [],
    "order": {
      "zh": "鹰形目",
      "en": "Accipitriformes"
    },
    "family": {
      "zh": "Hawks, Eagles, and Kites",
      "en": "Hawks, Eagles, and Kites"
    },
    "dataLevel": "C",
    "sourceRefs": [
      "eBird API v2 taxonomy",
      "eBird CN-13 Hebei checklist"
    ],
    "updatedAt": "2026-05-07"
  },
  {
    "birdId": "harduc",
    "chineseName": "Harlequin Duck",
    "englishName": "Harlequin Duck",
    "scientificName": "Histrionicus histrionicus",
    "aliases": [],
    "order": {
      "zh": "雁形目",
      "en": "Anseriformes"
    },
    "family": {
      "zh": "Ducks, Geese, and Waterfowl",
      "en": "Ducks, Geese, and Waterfowl"
    },
    "dataLevel": "C",
    "sourceRefs": [
      "eBird API v2 taxonomy",
      "eBird CN-13 Hebei checklist"
    ],
    "updatedAt": "2026-05-07"
  },
  {
    "birdId": "himgri1",
    "chineseName": "Himalayan Griffon",
    "englishName": "Himalayan Griffon",
    "scientificName": "Gyps himalayensis",
    "aliases": [],
    "order": {
      "zh": "鹰形目",
      "en": "Accipitriformes"
    },
    "family": {
      "zh": "Hawks, Eagles, and Kites",
      "en": "Hawks, Eagles, and Kites"
    },
    "dataLevel": "C",
    "sourceRefs": [
      "eBird API v2 taxonomy",
      "eBird CN-13 Hebei checklist"
    ],
    "updatedAt": "2026-05-07"
  },
  {
    "birdId": "hoocra1",
    "chineseName": "白头鹤",
    "englishName": "白頭鶴",
    "scientificName": "Grus monacha",
    "aliases": [],
    "order": {
      "zh": "鹤形目",
      "en": "Gruiformes"
    },
    "family": {
      "zh": "Cranes",
      "en": "Cranes"
    },
    "dataLevel": "C",
    "sourceRefs": [
      "eBird API v2 taxonomy",
      "eBird CN-13 Hebei checklist"
    ],
    "updatedAt": "2026-05-07"
  },
  {
    "birdId": "horgre",
    "chineseName": "角䴙䴘",
    "englishName": "角鸊鷉",
    "scientificName": "Podiceps auritus",
    "aliases": [],
    "order": {
      "zh": "䴙䴘目",
      "en": "Podicipediformes"
    },
    "family": {
      "zh": "Grebes",
      "en": "Grebes"
    },
    "dataLevel": "C",
    "sourceRefs": [
      "eBird API v2 taxonomy",
      "eBird CN-13 Hebei checklist"
    ],
    "updatedAt": "2026-05-07"
  },
  {
    "birdId": "impeag1",
    "chineseName": "白肩鵰",
    "englishName": "白肩鵰",
    "scientificName": "Aquila heliaca",
    "aliases": [],
    "order": {
      "zh": "鹰形目",
      "en": "Accipitriformes"
    },
    "family": {
      "zh": "Hawks, Eagles, and Kites",
      "en": "Hawks, Eagles, and Kites"
    },
    "dataLevel": "C",
    "sourceRefs": [
      "eBird API v2 taxonomy",
      "eBird CN-13 Hebei checklist"
    ],
    "updatedAt": "2026-05-07"
  },
  {
    "birdId": "integr1",
    "chineseName": "中白鹭",
    "englishName": "中白鷺",
    "scientificName": "Ardea intermedia",
    "aliases": [],
    "order": {
      "zh": "鹈形目",
      "en": "Pelecaniformes"
    },
    "family": {
      "zh": "Herons, Egrets, and Bitterns",
      "en": "Herons, Egrets, and Bitterns"
    },
    "dataLevel": "C",
    "sourceRefs": [
      "eBird API v2 taxonomy",
      "eBird CN-13 Hebei checklist"
    ],
    "updatedAt": "2026-05-07"
  },
  {
    "birdId": "japspa1",
    "chineseName": "日本松雀鷹",
    "englishName": "日本松雀鷹",
    "scientificName": "Tachyspiza gularis",
    "aliases": [],
    "order": {
      "zh": "鹰形目",
      "en": "Accipitriformes"
    },
    "family": {
      "zh": "Hawks, Eagles, and Kites",
      "en": "Hawks, Eagles, and Kites"
    },
    "dataLevel": "C",
    "sourceRefs": [
      "eBird API v2 taxonomy",
      "eBird CN-13 Hebei checklist"
    ],
    "updatedAt": "2026-05-07"
  },
  {
    "birdId": "litegr",
    "chineseName": "小白鹭",
    "englishName": "小白鷺",
    "scientificName": "Egretta garzetta",
    "aliases": [],
    "order": {
      "zh": "鹈形目",
      "en": "Pelecaniformes"
    },
    "family": {
      "zh": "Herons, Egrets, and Bitterns",
      "en": "Herons, Egrets, and Bitterns"
    },
    "dataLevel": "C",
    "sourceRefs": [
      "eBird API v2 taxonomy",
      "eBird CN-13 Hebei checklist"
    ],
    "updatedAt": "2026-05-07"
  },
  {
    "birdId": "litgre1",
    "chineseName": "小䴙䴘",
    "englishName": "小鸊鷉",
    "scientificName": "Tachybaptus ruficollis",
    "aliases": [],
    "order": {
      "zh": "䴙䴘目",
      "en": "Podicipediformes"
    },
    "family": {
      "zh": "Grebes",
      "en": "Grebes"
    },
    "dataLevel": "C",
    "sourceRefs": [
      "eBird API v2 taxonomy",
      "eBird CN-13 Hebei checklist"
    ],
    "updatedAt": "2026-05-07"
  },
  {
    "birdId": "lotduc",
    "chineseName": "长尾鸭",
    "englishName": "長尾鴨",
    "scientificName": "Clangula hyemalis",
    "aliases": [],
    "order": {
      "zh": "雁形目",
      "en": "Anseriformes"
    },
    "family": {
      "zh": "Ducks, Geese, and Waterfowl",
      "en": "Ducks, Geese, and Waterfowl"
    },
    "dataLevel": "C",
    "sourceRefs": [
      "eBird API v2 taxonomy",
      "eBird CN-13 Hebei checklist"
    ],
    "updatedAt": "2026-05-07"
  },
  {
    "birdId": "lwfgoo",
    "chineseName": "小白額雁",
    "englishName": "小白額雁",
    "scientificName": "Anser erythropus",
    "aliases": [],
    "order": {
      "zh": "雁形目",
      "en": "Anseriformes"
    },
    "family": {
      "zh": "Ducks, Geese, and Waterfowl",
      "en": "Ducks, Geese, and Waterfowl"
    },
    "dataLevel": "C",
    "sourceRefs": [
      "eBird API v2 taxonomy",
      "eBird CN-13 Hebei checklist"
    ],
    "updatedAt": "2026-05-07"
  },
  {
    "birdId": "mallar3",
    "chineseName": "绿头鸭",
    "englishName": "綠頭鴨",
    "scientificName": "Anas platyrhynchos",
    "aliases": [],
    "order": {
      "zh": "雁形目",
      "en": "Anseriformes"
    },
    "family": {
      "zh": "Ducks, Geese, and Waterfowl",
      "en": "Ducks, Geese, and Waterfowl"
    },
    "dataLevel": "C",
    "sourceRefs": [
      "eBird API v2 taxonomy",
      "eBird CN-13 Hebei checklist"
    ],
    "updatedAt": "2026-05-07"
  },
  {
    "birdId": "manduc",
    "chineseName": "鴛鴦",
    "englishName": "鴛鴦",
    "scientificName": "Aix galericulata",
    "aliases": [],
    "order": {
      "zh": "雁形目",
      "en": "Anseriformes"
    },
    "family": {
      "zh": "Ducks, Geese, and Waterfowl",
      "en": "Ducks, Geese, and Waterfowl"
    },
    "dataLevel": "C",
    "sourceRefs": [
      "eBird API v2 taxonomy",
      "eBird CN-13 Hebei checklist"
    ],
    "updatedAt": "2026-05-07"
  },
  {
    "birdId": "musduc",
    "chineseName": "疣鼻棲鸭",
    "englishName": "疣鼻棲鴨",
    "scientificName": "Cairina moschata",
    "aliases": [],
    "order": {
      "zh": "雁形目",
      "en": "Anseriformes"
    },
    "family": {
      "zh": "Ducks, Geese, and Waterfowl",
      "en": "Ducks, Geese, and Waterfowl"
    },
    "dataLevel": "C",
    "sourceRefs": [
      "eBird API v2 taxonomy",
      "eBird CN-13 Hebei checklist"
    ],
    "updatedAt": "2026-05-07"
  },
  {
    "birdId": "mutswa",
    "chineseName": "疣鼻天鵝",
    "englishName": "疣鼻天鵝",
    "scientificName": "Cygnus olor",
    "aliases": [],
    "order": {
      "zh": "雁形目",
      "en": "Anseriformes"
    },
    "family": {
      "zh": "Ducks, Geese, and Waterfowl",
      "en": "Ducks, Geese, and Waterfowl"
    },
    "dataLevel": "C",
    "sourceRefs": [
      "eBird API v2 taxonomy",
      "eBird CN-13 Hebei checklist"
    ],
    "updatedAt": "2026-05-07"
  },
  {
    "birdId": "norgos1",
    "chineseName": "蒼鷹",
    "englishName": "蒼鷹",
    "scientificName": "Astur gentilis",
    "aliases": [],
    "order": {
      "zh": "鹰形目",
      "en": "Accipitriformes"
    },
    "family": {
      "zh": "Hawks, Eagles, and Kites",
      "en": "Hawks, Eagles, and Kites"
    },
    "dataLevel": "C",
    "sourceRefs": [
      "eBird API v2 taxonomy",
      "eBird CN-13 Hebei checklist"
    ],
    "updatedAt": "2026-05-07"
  },
  {
    "birdId": "norhar1",
    "chineseName": "灰泽𫛭",
    "englishName": "灰澤鵟",
    "scientificName": "Circus cyaneus",
    "aliases": [],
    "order": {
      "zh": "鹰形目",
      "en": "Accipitriformes"
    },
    "family": {
      "zh": "Hawks, Eagles, and Kites",
      "en": "Hawks, Eagles, and Kites"
    },
    "dataLevel": "C",
    "sourceRefs": [
      "eBird API v2 taxonomy",
      "eBird CN-13 Hebei checklist"
    ],
    "updatedAt": "2026-05-07"
  },
  {
    "birdId": "norpin",
    "chineseName": "尖尾鸭",
    "englishName": "尖尾鴨",
    "scientificName": "Anas acuta",
    "aliases": [],
    "order": {
      "zh": "雁形目",
      "en": "Anseriformes"
    },
    "family": {
      "zh": "Ducks, Geese, and Waterfowl",
      "en": "Ducks, Geese, and Waterfowl"
    },
    "dataLevel": "C",
    "sourceRefs": [
      "eBird API v2 taxonomy",
      "eBird CN-13 Hebei checklist"
    ],
    "updatedAt": "2026-05-07"
  },
  {
    "birdId": "norsho",
    "chineseName": "琵嘴鸭",
    "englishName": "琵嘴鴨",
    "scientificName": "Spatula clypeata",
    "aliases": [],
    "order": {
      "zh": "雁形目",
      "en": "Anseriformes"
    },
    "family": {
      "zh": "Ducks, Geese, and Waterfowl",
      "en": "Ducks, Geese, and Waterfowl"
    },
    "dataLevel": "C",
    "sourceRefs": [
      "eBird API v2 taxonomy",
      "eBird CN-13 Hebei checklist"
    ],
    "updatedAt": "2026-05-07"
  },
  {
    "birdId": "orihob2",
    "chineseName": "东方蜂鷹",
    "englishName": "東方蜂鷹",
    "scientificName": "Pernis ptilorhynchus",
    "aliases": [],
    "order": {
      "zh": "鹰形目",
      "en": "Accipitriformes"
    },
    "family": {
      "zh": "Hawks, Eagles, and Kites",
      "en": "Hawks, Eagles, and Kites"
    },
    "dataLevel": "C",
    "sourceRefs": [
      "eBird API v2 taxonomy",
      "eBird CN-13 Hebei checklist"
    ],
    "updatedAt": "2026-05-07"
  },
  {
    "birdId": "osprey",
    "chineseName": "鱼鷹",
    "englishName": "魚鷹",
    "scientificName": "Pandion haliaetus",
    "aliases": [],
    "order": {
      "zh": "鹰形目",
      "en": "Accipitriformes"
    },
    "family": {
      "zh": "Osprey",
      "en": "Osprey"
    },
    "dataLevel": "C",
    "sourceRefs": [
      "eBird API v2 taxonomy",
      "eBird CN-13 Hebei checklist"
    ],
    "updatedAt": "2026-05-07"
  },
  {
    "birdId": "piehar1",
    "chineseName": "花泽𫛭",
    "englishName": "花澤鵟",
    "scientificName": "Circus melanoleucos",
    "aliases": [],
    "order": {
      "zh": "鹰形目",
      "en": "Accipitriformes"
    },
    "family": {
      "zh": "Hawks, Eagles, and Kites",
      "en": "Hawks, Eagles, and Kites"
    },
    "dataLevel": "C",
    "sourceRefs": [
      "eBird API v2 taxonomy",
      "eBird CN-13 Hebei checklist"
    ],
    "updatedAt": "2026-05-07"
  },
  {
    "birdId": "purher1",
    "chineseName": "紫鹭",
    "englishName": "紫鷺",
    "scientificName": "Ardea purpurea",
    "aliases": [],
    "order": {
      "zh": "鹈形目",
      "en": "Pelecaniformes"
    },
    "family": {
      "zh": "Herons, Egrets, and Bitterns",
      "en": "Herons, Egrets, and Bitterns"
    },
    "dataLevel": "C",
    "sourceRefs": [
      "eBird API v2 taxonomy",
      "eBird CN-13 Hebei checklist"
    ],
    "updatedAt": "2026-05-07"
  },
  {
    "birdId": "rebgoo1",
    "chineseName": "Red-breasted Goose",
    "englishName": "Red-breasted Goose",
    "scientificName": "Branta ruficollis",
    "aliases": [],
    "order": {
      "zh": "雁形目",
      "en": "Anseriformes"
    },
    "family": {
      "zh": "Ducks, Geese, and Waterfowl",
      "en": "Ducks, Geese, and Waterfowl"
    },
    "dataLevel": "C",
    "sourceRefs": [
      "eBird API v2 taxonomy",
      "eBird CN-13 Hebei checklist"
    ],
    "updatedAt": "2026-05-07"
  },
  {
    "birdId": "rebmer",
    "chineseName": "红胸秋沙",
    "englishName": "紅胸秋沙",
    "scientificName": "Mergus serrator",
    "aliases": [],
    "order": {
      "zh": "雁形目",
      "en": "Anseriformes"
    },
    "family": {
      "zh": "Ducks, Geese, and Waterfowl",
      "en": "Ducks, Geese, and Waterfowl"
    },
    "dataLevel": "C",
    "sourceRefs": [
      "eBird API v2 taxonomy",
      "eBird CN-13 Hebei checklist"
    ],
    "updatedAt": "2026-05-07"
  },
  {
    "birdId": "reccra1",
    "chineseName": "丹頂鹤",
    "englishName": "丹頂鶴",
    "scientificName": "Grus japonensis",
    "aliases": [],
    "order": {
      "zh": "鹤形目",
      "en": "Gruiformes"
    },
    "family": {
      "zh": "Cranes",
      "en": "Cranes"
    },
    "dataLevel": "C",
    "sourceRefs": [
      "eBird API v2 taxonomy",
      "eBird CN-13 Hebei checklist"
    ],
    "updatedAt": "2026-05-07"
  },
  {
    "birdId": "recpoc",
    "chineseName": "赤嘴潛鸭",
    "englishName": "赤嘴潛鴨",
    "scientificName": "Netta rufina",
    "aliases": [],
    "order": {
      "zh": "雁形目",
      "en": "Anseriformes"
    },
    "family": {
      "zh": "Ducks, Geese, and Waterfowl",
      "en": "Ducks, Geese, and Waterfowl"
    },
    "dataLevel": "C",
    "sourceRefs": [
      "eBird API v2 taxonomy",
      "eBird CN-13 Hebei checklist"
    ],
    "updatedAt": "2026-05-07"
  },
  {
    "birdId": "rengre",
    "chineseName": "赤颈䴙䴘",
    "englishName": "赤頸鸊鷉",
    "scientificName": "Podiceps grisegena",
    "aliases": [],
    "order": {
      "zh": "䴙䴘目",
      "en": "Podicipediformes"
    },
    "family": {
      "zh": "Grebes",
      "en": "Grebes"
    },
    "dataLevel": "C",
    "sourceRefs": [
      "eBird API v2 taxonomy",
      "eBird CN-13 Hebei checklist"
    ],
    "updatedAt": "2026-05-07"
  },
  {
    "birdId": "rolhaw",
    "chineseName": "毛足𫛭",
    "englishName": "毛足鵟",
    "scientificName": "Buteo lagopus",
    "aliases": [],
    "order": {
      "zh": "鹰形目",
      "en": "Accipitriformes"
    },
    "family": {
      "zh": "Hawks, Eagles, and Kites",
      "en": "Hawks, Eagles, and Kites"
    },
    "dataLevel": "C",
    "sourceRefs": [
      "eBird API v2 taxonomy",
      "eBird CN-13 Hebei checklist"
    ],
    "updatedAt": "2026-05-07"
  },
  {
    "birdId": "rubcra1",
    "chineseName": "緋秧雞",
    "englishName": "緋秧雞",
    "scientificName": "Zapornia fusca",
    "aliases": [],
    "order": {
      "zh": "鹤形目",
      "en": "Gruiformes"
    },
    "family": {
      "zh": "Rails, Gallinules, and Coots",
      "en": "Rails, Gallinules, and Coots"
    },
    "dataLevel": "C",
    "sourceRefs": [
      "eBird API v2 taxonomy",
      "eBird CN-13 Hebei checklist"
    ],
    "updatedAt": "2026-05-07"
  },
  {
    "birdId": "rudshe",
    "chineseName": "瀆凫",
    "englishName": "瀆鳧",
    "scientificName": "Tadorna ferruginea",
    "aliases": [],
    "order": {
      "zh": "雁形目",
      "en": "Anseriformes"
    },
    "family": {
      "zh": "Ducks, Geese, and Waterfowl",
      "en": "Ducks, Geese, and Waterfowl"
    },
    "dataLevel": "C",
    "sourceRefs": [
      "eBird API v2 taxonomy",
      "eBird CN-13 Hebei checklist"
    ],
    "updatedAt": "2026-05-07"
  },
  {
    "birdId": "sancra",
    "chineseName": "沙丘鹤",
    "englishName": "沙丘鶴",
    "scientificName": "Antigone canadensis",
    "aliases": [],
    "order": {
      "zh": "鹤形目",
      "en": "Gruiformes"
    },
    "family": {
      "zh": "Cranes",
      "en": "Cranes"
    },
    "dataLevel": "C",
    "sourceRefs": [
      "eBird API v2 taxonomy",
      "eBird CN-13 Hebei checklist"
    ],
    "updatedAt": "2026-05-07"
  },
  {
    "birdId": "schbit1",
    "chineseName": "秋小鹭",
    "englishName": "秋小鷺",
    "scientificName": "Botaurus eurhythmus",
    "aliases": [],
    "order": {
      "zh": "鹈形目",
      "en": "Pelecaniformes"
    },
    "family": {
      "zh": "Herons, Egrets, and Bitterns",
      "en": "Herons, Egrets, and Bitterns"
    },
    "dataLevel": "C",
    "sourceRefs": [
      "eBird API v2 taxonomy",
      "eBird CN-13 Hebei checklist"
    ],
    "updatedAt": "2026-05-07"
  },
  {
    "birdId": "shteag1",
    "chineseName": "Short-toed Snake-Eagle",
    "englishName": "Short-toed Snake-Eagle",
    "scientificName": "Circaetus gallicus",
    "aliases": [],
    "order": {
      "zh": "鹰形目",
      "en": "Accipitriformes"
    },
    "family": {
      "zh": "Hawks, Eagles, and Kites",
      "en": "Hawks, Eagles, and Kites"
    },
    "dataLevel": "C",
    "sourceRefs": [
      "eBird API v2 taxonomy",
      "eBird CN-13 Hebei checklist"
    ],
    "updatedAt": "2026-05-07"
  },
  {
    "birdId": "sibcra1",
    "chineseName": "白鹤",
    "englishName": "白鶴",
    "scientificName": "Leucogeranus leucogeranus",
    "aliases": [],
    "order": {
      "zh": "鹤形目",
      "en": "Gruiformes"
    },
    "family": {
      "zh": "Cranes",
      "en": "Cranes"
    },
    "dataLevel": "C",
    "sourceRefs": [
      "eBird API v2 taxonomy",
      "eBird CN-13 Hebei checklist"
    ],
    "updatedAt": "2026-05-07"
  },
  {
    "birdId": "smew",
    "chineseName": "白秋沙",
    "englishName": "白秋沙",
    "scientificName": "Mergellus albellus",
    "aliases": [],
    "order": {
      "zh": "雁形目",
      "en": "Anseriformes"
    },
    "family": {
      "zh": "Ducks, Geese, and Waterfowl",
      "en": "Ducks, Geese, and Waterfowl"
    },
    "dataLevel": "C",
    "sourceRefs": [
      "eBird API v2 taxonomy",
      "eBird CN-13 Hebei checklist"
    ],
    "updatedAt": "2026-05-07"
  },
  {
    "birdId": "spbduc",
    "chineseName": "花嘴鸭",
    "englishName": "花嘴鴨",
    "scientificName": "Anas zonorhyncha",
    "aliases": [],
    "order": {
      "zh": "雁形目",
      "en": "Anseriformes"
    },
    "family": {
      "zh": "Ducks, Geese, and Waterfowl",
      "en": "Ducks, Geese, and Waterfowl"
    },
    "dataLevel": "C",
    "sourceRefs": [
      "eBird API v2 taxonomy",
      "eBird CN-13 Hebei checklist"
    ],
    "updatedAt": "2026-05-07"
  },
  {
    "birdId": "steeag1",
    "chineseName": "Steppe Eagle",
    "englishName": "Steppe Eagle",
    "scientificName": "Aquila nipalensis",
    "aliases": [],
    "order": {
      "zh": "鹰形目",
      "en": "Accipitriformes"
    },
    "family": {
      "zh": "Hawks, Eagles, and Kites",
      "en": "Hawks, Eagles, and Kites"
    },
    "dataLevel": "C",
    "sourceRefs": [
      "eBird API v2 taxonomy",
      "eBird CN-13 Hebei checklist"
    ],
    "updatedAt": "2026-05-07"
  },
  {
    "birdId": "strher1",
    "chineseName": "绿簑鹭",
    "englishName": "綠簑鷺",
    "scientificName": "Butorides atricapilla",
    "aliases": [],
    "order": {
      "zh": "鹈形目",
      "en": "Pelecaniformes"
    },
    "family": {
      "zh": "Herons, Egrets, and Bitterns",
      "en": "Herons, Egrets, and Bitterns"
    },
    "dataLevel": "C",
    "sourceRefs": [
      "eBird API v2 taxonomy",
      "eBird CN-13 Hebei checklist"
    ],
    "updatedAt": "2026-05-07"
  },
  {
    "birdId": "swagoo1",
    "chineseName": "鴻雁",
    "englishName": "鴻雁",
    "scientificName": "Anser cygnoides",
    "aliases": [],
    "order": {
      "zh": "雁形目",
      "en": "Anseriformes"
    },
    "family": {
      "zh": "Ducks, Geese, and Waterfowl",
      "en": "Ducks, Geese, and Waterfowl"
    },
    "dataLevel": "C",
    "sourceRefs": [
      "eBird API v2 taxonomy",
      "eBird CN-13 Hebei checklist"
    ],
    "updatedAt": "2026-05-07"
  },
  {
    "birdId": "swirai1",
    "chineseName": "Swinhoe's Rail",
    "englishName": "Swinhoe's Rail",
    "scientificName": "Coturnicops exquisitus",
    "aliases": [],
    "order": {
      "zh": "鹤形目",
      "en": "Gruiformes"
    },
    "family": {
      "zh": "Rails, Gallinules, and Coots",
      "en": "Rails, Gallinules, and Coots"
    },
    "dataLevel": "C",
    "sourceRefs": [
      "eBird API v2 taxonomy",
      "eBird CN-13 Hebei checklist"
    ],
    "updatedAt": "2026-05-07"
  },
  {
    "birdId": "taibeg1",
    "chineseName": "寒林豆雁",
    "englishName": "寒林豆雁",
    "scientificName": "Anser fabalis",
    "aliases": [],
    "order": {
      "zh": "雁形目",
      "en": "Anseriformes"
    },
    "family": {
      "zh": "Ducks, Geese, and Waterfowl",
      "en": "Ducks, Geese, and Waterfowl"
    },
    "dataLevel": "C",
    "sourceRefs": [
      "eBird API v2 taxonomy",
      "eBird CN-13 Hebei checklist"
    ],
    "updatedAt": "2026-05-07"
  },
  {
    "birdId": "tufduc",
    "chineseName": "凤头潛鸭",
    "englishName": "鳳頭潛鴨",
    "scientificName": "Aythya fuligula",
    "aliases": [],
    "order": {
      "zh": "雁形目",
      "en": "Anseriformes"
    },
    "family": {
      "zh": "Ducks, Geese, and Waterfowl",
      "en": "Ducks, Geese, and Waterfowl"
    },
    "dataLevel": "C",
    "sourceRefs": [
      "eBird API v2 taxonomy",
      "eBird CN-13 Hebei checklist"
    ],
    "updatedAt": "2026-05-07"
  },
  {
    "birdId": "tunbeg1",
    "chineseName": "凍原豆雁",
    "englishName": "凍原豆雁",
    "scientificName": "Anser serrirostris",
    "aliases": [],
    "order": {
      "zh": "雁形目",
      "en": "Anseriformes"
    },
    "family": {
      "zh": "Ducks, Geese, and Waterfowl",
      "en": "Ducks, Geese, and Waterfowl"
    },
    "dataLevel": "C",
    "sourceRefs": [
      "eBird API v2 taxonomy",
      "eBird CN-13 Hebei checklist"
    ],
    "updatedAt": "2026-05-07"
  },
  {
    "birdId": "tunswa",
    "chineseName": "小天鵝",
    "englishName": "小天鵝",
    "scientificName": "Cygnus columbianus",
    "aliases": [],
    "order": {
      "zh": "雁形目",
      "en": "Anseriformes"
    },
    "family": {
      "zh": "Ducks, Geese, and Waterfowl",
      "en": "Ducks, Geese, and Waterfowl"
    },
    "dataLevel": "C",
    "sourceRefs": [
      "eBird API v2 taxonomy",
      "eBird CN-13 Hebei checklist"
    ],
    "updatedAt": "2026-05-07"
  },
  {
    "birdId": "uplbuz1",
    "chineseName": "大𫛭",
    "englishName": "大鵟",
    "scientificName": "Buteo hemilasius",
    "aliases": [],
    "order": {
      "zh": "鹰形目",
      "en": "Accipitriformes"
    },
    "family": {
      "zh": "Hawks, Eagles, and Kites",
      "en": "Hawks, Eagles, and Kites"
    },
    "dataLevel": "C",
    "sourceRefs": [
      "eBird API v2 taxonomy",
      "eBird CN-13 Hebei checklist"
    ],
    "updatedAt": "2026-05-07"
  },
  {
    "birdId": "waterc1",
    "chineseName": "董雞",
    "englishName": "董雞",
    "scientificName": "Gallicrex cinerea",
    "aliases": [],
    "order": {
      "zh": "鹤形目",
      "en": "Gruiformes"
    },
    "family": {
      "zh": "Rails, Gallinules, and Coots",
      "en": "Rails, Gallinules, and Coots"
    },
    "dataLevel": "C",
    "sourceRefs": [
      "eBird API v2 taxonomy",
      "eBird CN-13 Hebei checklist"
    ],
    "updatedAt": "2026-05-07"
  },
  {
    "birdId": "watrai1",
    "chineseName": "西方秧雞",
    "englishName": "西方秧雞",
    "scientificName": "Rallus aquaticus",
    "aliases": [],
    "order": {
      "zh": "鹤形目",
      "en": "Gruiformes"
    },
    "family": {
      "zh": "Rails, Gallinules, and Coots",
      "en": "Rails, Gallinules, and Coots"
    },
    "dataLevel": "C",
    "sourceRefs": [
      "eBird API v2 taxonomy",
      "eBird CN-13 Hebei checklist"
    ],
    "updatedAt": "2026-05-07"
  },
  {
    "birdId": "whbwat1",
    "chineseName": "白腹秧雞",
    "englishName": "白腹秧雞",
    "scientificName": "Amaurornis phoenicurus",
    "aliases": [],
    "order": {
      "zh": "鹤形目",
      "en": "Gruiformes"
    },
    "family": {
      "zh": "Rails, Gallinules, and Coots",
      "en": "Rails, Gallinules, and Coots"
    },
    "dataLevel": "C",
    "sourceRefs": [
      "eBird API v2 taxonomy",
      "eBird CN-13 Hebei checklist"
    ],
    "updatedAt": "2026-05-07"
  },
  {
    "birdId": "whncra1",
    "chineseName": "白枕鹤",
    "englishName": "白枕鶴",
    "scientificName": "Antigone vipio",
    "aliases": [],
    "order": {
      "zh": "鹤形目",
      "en": "Gruiformes"
    },
    "family": {
      "zh": "Cranes",
      "en": "Cranes"
    },
    "dataLevel": "C",
    "sourceRefs": [
      "eBird API v2 taxonomy",
      "eBird CN-13 Hebei checklist"
    ],
    "updatedAt": "2026-05-07"
  },
  {
    "birdId": "whoswa",
    "chineseName": "黄嘴天鵝",
    "englishName": "黃嘴天鵝",
    "scientificName": "Cygnus cygnus",
    "aliases": [],
    "order": {
      "zh": "雁形目",
      "en": "Anseriformes"
    },
    "family": {
      "zh": "Ducks, Geese, and Waterfowl",
      "en": "Ducks, Geese, and Waterfowl"
    },
    "dataLevel": "C",
    "sourceRefs": [
      "eBird API v2 taxonomy",
      "eBird CN-13 Hebei checklist"
    ],
    "updatedAt": "2026-05-07"
  },
  {
    "birdId": "whteag",
    "chineseName": "白尾海鵰",
    "englishName": "白尾海鵰",
    "scientificName": "Haliaeetus albicilla",
    "aliases": [],
    "order": {
      "zh": "鹰形目",
      "en": "Accipitriformes"
    },
    "family": {
      "zh": "Hawks, Eagles, and Kites",
      "en": "Hawks, Eagles, and Kites"
    },
    "dataLevel": "C",
    "sourceRefs": [
      "eBird API v2 taxonomy",
      "eBird CN-13 Hebei checklist"
    ],
    "updatedAt": "2026-05-07"
  },
  {
    "birdId": "whwsco1",
    "chineseName": "Stejneger's Scoter",
    "englishName": "Stejneger's Scoter",
    "scientificName": "Melanitta stejnegeri",
    "aliases": [],
    "order": {
      "zh": "雁形目",
      "en": "Anseriformes"
    },
    "family": {
      "zh": "Ducks, Geese, and Waterfowl",
      "en": "Ducks, Geese, and Waterfowl"
    },
    "dataLevel": "C",
    "sourceRefs": [
      "eBird API v2 taxonomy",
      "eBird CN-13 Hebei checklist"
    ],
    "updatedAt": "2026-05-07"
  },
  {
    "birdId": "yelbit",
    "chineseName": "黄小鹭",
    "englishName": "黃小鷺",
    "scientificName": "Botaurus sinensis",
    "aliases": [],
    "order": {
      "zh": "鹈形目",
      "en": "Pelecaniformes"
    },
    "family": {
      "zh": "Herons, Egrets, and Bitterns",
      "en": "Herons, Egrets, and Bitterns"
    },
    "dataLevel": "C",
    "sourceRefs": [
      "eBird API v2 taxonomy",
      "eBird CN-13 Hebei checklist"
    ],
    "updatedAt": "2026-05-07"
  }
]